Workbook
Name Display: [1]!テーブル3[Display]
Name Elec: [1]!テーブル7[Elec]
Name Material: [1]!テーブル5[Material]
Name Mecha: [1]!テーブル6[Mecha]
Name Package: [1]!テーブル2[Package]
Name Product: [1]!テーブル4[Product]
Name SQLリスト: SQL[SQL Type]
Name 分類1: [1]!テーブル1[分類１]

Sheet <SQL> 
B3: =COLUMNS($B$2:B$2) -> 1 | C3: =COLUMNS($B$2:C$2) -> 2 | D3: =COLUMNS($B$2:D$2) -> 3 | E3: =COLUMNS($B$2:E$2) -> 4 | F3: =COLUMNS($B$2:F$2) -> 5 | G3: =COLUMNS($B$2:G$2) -> 6
B5: SQL Type | C5: offset | D5: 列12 | E5: テーブル | F5: 列14
B6: SQLite | C6: 0 | E6: =COLUMNS($B$2:E$2) -> 4 | G6: 6
B7: SQL Server | C7: 1 | E7: =COLUMNS($B$2:F$2) -> 5
B8: MongoDB | C8: 2 | E8: =COLUMNS($B$2:G$2) -> 6
B11: Type | C11: Desc | D11: Note | E11: SQLite | F11: SQL Server | G11: MongoDB
B12: INT | C12: 整数型 | D12: 一般的な整数型。範囲は -2,147,483,648 から 2,147,483,647。 | E12: INTEGER
B13: SMALLINT | C13: 整数型 | D13: 小さめの整数型。範囲は -32,768 から 32,767。 | E13: INTEGER
B14: TINYINT | C14: 整数型 | D14: 非常に小さい整数型。範囲は 0 から 255（符号なし）または -128 から 127（符号あり）。 | E14: INTEGER
B15: BIGINT | C15: 整数型 | D15: 大きな整数型。範囲は -9,223,372,036,854,775,808 から 9,223,372,036,854,775,807。 | E15: INTEGER
B16: FLOAT | C16: 浮動小数点型 | D16: 単精度の浮動小数点型。精度と範囲は実装に依存。 | E16: REAL
B17: REAL | C17: 浮動小数点型 | D17: 浮動小数点型。通常、FLOATと同義で使用されるが、精度は実装に依存。 | E17: REAL
B18: DECIMAL | C18: 固定小数点型 | D18: 精度を指定できる固定小数点型。主に金額などの精度が重要なデータに使用。 | E18: REAL
B19: NUMERIC | C19: 固定小数点型 | D19: DECIMALと同義。精度を指定できる固定小数点型 | E19: REAL
B20: CHAR | C20: 固定長文字列型 | D20: 固定長の文字列を格納するためのデータ型です。データの長さが指定された文字数に満たない場合、残りのスペースは空白文字で埋められます。 | E20: TEXT
B21: VARCHAR | C21: 可変長文字列型 | D21: 可変長の文字列を格納するためのデータ型です。格納するデータの長さに応じて、必要な分だけのストレージが使用されます。指定された長さの上限を超えるデータは格納できません。 | E21: TEXT
B22: TEXT | C22: 大文字列型 | D22: 非常に長い可変長の文字列を格納するためのデータ型です。通常、VARCHAR よりも大きなサイズの文字列を格納するために使用されます。データベースごとに制限が異なりますが、かなりの大容量を扱うことが可能です。 | E22: TEXT
B23: CLOB | C23: 大文字列型 | D23: 大規模な文字データを格納するためのデータ型です。TEXT と同様に非常に長い文字列を扱うことができますが、データベースシステムによっては異なる内部処理や制限がある場合があります。 | E23: TEXT
... B34: BLOB | C34: 大バイナリ型 | D34: 大きなバイナリデータ（Binary Large Object）を格納する | E34: BLOB
B35: NULL | E35: NULL
B38: NOT NULL | C38: Desc | D38: Note | E38: SQLite | F38: SQL Server | G38: MongoDB
B39: Y | C39: 対応 | E39: NOT NULL
B40: N | C40: 非対応
C41: 非対応
B44: PK | C44: Desc | D44: Note | E44: SQLite | F44: SQL Server | G44: MongoDB
B45: Y | C45: 対応 | E45: PRIMARY KEY
B46: N | C46: 非対応
C47: 非対応
B50: FK | C50: Desc | D50: Note | E50: SQLite | F50: SQL Server | G50: MongoDB
B51: Y | C51: 対応
B52: N | C52: 非対応
C53: 非対応

Sheet Table>
A2: https://www.blog.furusuzu0530.com/development-2/
O3: KEY_KEY_CAT_TYPE : Final[str] = "KEY_CAT_TYPE"# キー大分類キー
B5: 論理名 | C5: SQLite | O5: 100
O6: 44
N7: CSV | O7: PYTHON
A8: 基準種類DB
B9: テーブル名 | C9: 物理名 | D9: tbl_cat_type | N9: =UPPER( D9 ) & "," &D9 & ",," -> TBL_CAT_TYPE,tbl_cat_type,, | O9: =LEFT( LEFT("KEY_"&UPPER(D9)&REPT(" ",$O$6),$O$6) & ": Final[str] = """&UPPER(D9)&"""" & REPT(" ",$O$5),$O$5 ) & "# " &D10 -> KEY_TBL_CAT_TYPE : Final[str] = "TBL_CAT_TYPE" # 基準類テーブル
C10: 論理名 | D10: 基準類テーブル
B11: カラム名 | E11: データ型 | J11: 制約 | N11: CREATE
B12: 物理名 | C12: 論理名 | D12: 概要 | E12: Type | F12: Byte | G12: SQLite | H12: SQL Server | I12: MongoDB | J12: NOT_NULL | K12: PK | L12: FK | N12: CSV | P12: SQLite | Q12: SQL Server | R12: MongoDB
B13: =OFFSET( tbl_cat_type[[#Headers],[key_cat_type]], 0, ROWS( $A$13:A13 )-1 ) -> key_cat_type | C13: 大分類キー | D13: キー大分類キー | E13: INT | F13: 4 | G13: =VLOOKUP($E13, sql_type[#All], '<SQL> '!$E$3, FALSE ) -> INTEGER | I13: =OFFSET( E13,0,1) -> 4 | J13: Y | K13: Y | M13: {="ITM_"&UPPER(RIGHT(OFFSET(D13,S13,0),LEN(OFFSET(D13,S13,0))-4))&"_"&_xlfn.IFNA(_xlfn.IFS(K13="Y","PKEY",L13="Y","F"&UPPER(B13)),UPPER(B13))} -> ITM_CAT_TYPE_PKEY | N13: =M13&","&B13&","&OFFSET(G13,0,VLOOKUP($C$5,SQL[#All],2,FALSE) ) &", -- "&D13 -> ITM_CAT_TYPE_PKEY,key_cat_type,INTEGER, -- キー大分類キー | O13: =LEFT(LEFT("KEY_"&M13&REPT(" ",$O$6),$O$6)&": Final[str] = """&M13&""""&REPT(" ",$O$5),$O$5)&"# "&D13 -> KEY_ITM_CAT_TYPE_PKEY : Final[str] = "ITM_CAT_TYPE_PKEY" # キー大分類キー | P13: =$B13 & " " & VLOOKUP($E13, sql_type[#All], '<SQL> '!$E$3, FALSE )& " " & IFERROR( IF($K13="", VLOOKUP(K13, sql_notnull[#All], '<SQL> '!$E$3, FALSE ), VLOOKUP($K13, sql_pk[], '<SQL> '!$E$3, FALSE ) ), "" ) & ", -- " &$D13 -> key_cat_type INTEGER PRIMARY KEY, -- キー大分類キー | S13: -4
B14: =OFFSET( tbl_cat_type[[#Headers],[key_cat_type]], 0, ROWS( $A$13:A14 )-1 ) -> title_jp | C14: 日本語名称 | D14: 日本語名称 | E14: VARCHAR | F14: 100 | G14: =VLOOKUP($E14, sql_type[#All], '<SQL> '!$E$3, FALSE ) -> TEXT | J14: Y | M14: {="ITM_"&UPPER(RIGHT(OFFSET(D14,S14,0),LEN(OFFSET(D14,S14,0))-4))&"_"&_xlfn.IFNA(_xlfn.IFS(K14="Y","PKEY",L14="Y","F"&UPPER(B14)),UPPER(B14))} -> ITM_CAT_TYPE_TITLE_JP | N14: =M14&","&B14&","&OFFSET(G14,0,VLOOKUP($C$5,SQL[#All],2,FALSE) ) &", -- "&D14 -> ITM_CAT_TYPE_TITLE_JP,title_jp,TEXT, -- 日本語名称 | O14: =LEFT(LEFT("KEY_"&M14&REPT(" ",$O$6),$O$6)&": Final[str] = """&M14&""""&REPT(" ",$O$5),$O$5)&"# "&D14 -> KEY_ITM_CAT_TYPE_TITLE_JP : Final[str] = "ITM_CAT_TYPE_TITLE_JP" # 日本語名称 | P14: =$B14 & " " & VLOOKUP($E14, sql_type[#All], '<SQL> '!$E$3, FALSE )& " " & IFERROR( IF($K14="", VLOOKUP(K14, sql_notnull[#All], '<SQL> '!$E$3, FALSE ), VLOOKUP($K14, sql_pk[], '<SQL> '!$E$3, FALSE ) ), "" ) & ", -- " &$D14 -> title_jp TEXT , -- 日本語名称 | S14: -5
B15: =OFFSET( tbl_cat_type[[#Headers],[key_cat_type]], 0, ROWS( $A$13:A15 )-1 ) -> title_en | C15: 英語コード | D15: 英語コード | E15: VARCHAR | F15: 100 | G15: =VLOOKUP($E15, sql_type[#All], '<SQL> '!$E$3, FALSE ) -> TEXT | J15: Y | M15: {="ITM_"&UPPER(RIGHT(OFFSET(D15,S15,0),LEN(OFFSET(D15,S15,0))-4))&"_"&_xlfn.IFNA(_xlfn.IFS(K15="Y","PKEY",L15="Y","F"&UPPER(B15)),UPPER(B15))} -> ITM_CAT_TYPE_TITLE_EN | N15: =M15&","&B15&","&OFFSET(G15,0,VLOOKUP($C$5,SQL[#All],2,FALSE) ) &", -- "&D15 -> ITM_CAT_TYPE_TITLE_EN,title_en,TEXT, -- 英語コード | O15: =LEFT(LEFT("KEY_"&M15&REPT(" ",$O$6),$O$6)&": Final[str] = """&M15&""""&REPT(" ",$O$5),$O$5)&"# "&D15 -> KEY_ITM_CAT_TYPE_TITLE_EN : Final[str] = "ITM_CAT_TYPE_TITLE_EN" # 英語コード | P15: =$B15 & " " & VLOOKUP($E15, sql_type[#All], '<SQL> '!$E$3, FALSE )& " " & IFERROR( IF($K15="", VLOOKUP(K15, sql_notnull[#All], '<SQL> '!$E$3, FALSE ), VLOOKUP($K15, sql_pk[], '<SQL> '!$E$3, FALSE ) ), "" ) & ", -- " &$D15 -> title_en TEXT , -- 英語コード | S15: -6
B16: path | C16: 保存先フォルダのパス | D16: 保存先フォルダのパス | E16: TEXT | G16: =VLOOKUP($E16, sql_type[#All], '<SQL> '!$E$3, FALSE ) -> TEXT | J16: Y | M16: {="ITM_"&UPPER(RIGHT(OFFSET(D16,S16,0),LEN(OFFSET(D16,S16,0))-4))&"_"&_xlfn.IFNA(_xlfn.IFS(K16="Y","PKEY",L16="Y","F"&UPPER(B16)),UPPER(B16))} -> ITM_CAT_TYPE_PATH | N16: =M16&","&B16&","&OFFSET(G16,0,VLOOKUP($C$5,SQL[#All],2,FALSE) ) &", -- "&D16 -> ITM_CAT_TYPE_PATH,path,TEXT, -- 保存先フォルダのパス | O16: =LEFT(LEFT("KEY_"&M16&REPT(" ",$O$6),$O$6)&": Final[str] = """&M16&""""&REPT(" ",$O$5),$O$5)&"# "&D16 -> KEY_ITM_CAT_TYPE_PATH : Final[str] = "ITM_CAT_TYPE_PATH" # 保存先フォルダのパス | P16: =$B16 & " " & VLOOKUP($E16, sql_type[#All], '<SQL> '!$E$3, FALSE )& " " & IFERROR( IF($K16="", VLOOKUP(K16, sql_notnull[#All], '<SQL> '!$E$3, FALSE ), VLOOKUP($K16, sql_pk[], '<SQL> '!$E$3, FALSE ) ), "" ) & ", -- " &$D16 -> path TEXT , -- 保存先フォルダのパス | S16: -7
S17: -8
A19: 基準大分類DB
B20: テーブル名 | C20: 物理名 | D20: tbl_cat_major | N20: =UPPER( D20 ) & "," &D20 & ",," -> TBL_CAT_MAJOR,tbl_cat_major,, | O20: =LEFT( LEFT("KEY_"&UPPER(D20)&REPT(" ",$O$6),$O$6) & ": Final[str] = """&UPPER(D20)&"""" & REPT(" ",$O$5),$O$5 ) & "# " &D21 -> KEY_TBL_CAT_MAJOR : Final[str] = "TBL_CAT_MAJOR" # 基準大分類テーブル
C21: 論理名 | D21: 基準大分類テーブル
B22: カラム名 | E22: データ型 | J22: 制約 | N22: CREATE
B23: 物理名 | C23: 論理名 | D23: 概要 | E23: Type | F23: Byte | G23: SQLite | H23: SQL Server | I23: MongoDB | J23: NOT_NULL | K23: PK | L23: FK | N23: CSV | P23: SQLite | Q23: SQL Server | R23: MongoDB
B24: =OFFSET( tbl_cat_major[[#Headers],[key_cat_major]], 0, ROWS( $A$24:A24 )-1 ) -> key_cat_major | C24: 中分類キー | D24: 中分類キー | E24: INT | F24: 4 | G24: =VLOOKUP($E24, sql_type[#All], '<SQL> '!$E$3, FALSE ) -> INTEGER | J24: Y | K24: Y | M24: {="ITM_"&UPPER(RIGHT(OFFSET(D24,S24,0),LEN(OFFSET(D24,S24,0))-4))&"_"&_xlfn.IFNA(_xlfn.IFS(K24="Y","PKEY",L24="Y","F"&UPPER(B24)),UPPER(B24))} -> ITM_CAT_MAJOR_PKEY | N24: =M24&","&B24&","&OFFSET(G24,0,VLOOKUP($C$5,SQL[#All],2,FALSE) ) &", -- "&D24 -> ITM_CAT_MAJOR_PKEY,key_cat_major,INTEGER, -- 中分類キー | O24: =LEFT(LEFT("KEY_"&M24&REPT(" ",$O$6),$O$6)&": Final[str] = """&M24&""""&REPT(" ",$O$5),$O$5)&"# "&D24 -> KEY_ITM_CAT_MAJOR_PKEY : Final[str] = "ITM_CAT_MAJOR_PKEY" # 中分類キー | P24: =$B24 & " " & VLOOKUP($E24, sql_type[#All], '<SQL> '!$E$3, FALSE )& " " & IFERROR( IF($K24="", VLOOKUP(K24, sql_notnull[#All], '<SQL> '!$E$3, FALSE ), VLOOKUP($K24, sql_pk[], '<SQL> '!$E$3, FALSE ) ), "" ) & ", -- " &$D24 -> key_cat_major INTEGER PRIMARY KEY, -- 中分類キー | S24: -4
B25: =OFFSET( tbl_cat_major[[#Headers],[key_cat_major]], 0, ROWS( $A$24:A25 )-1 ) -> title_jp | C25: 日本語名称 | D25: 日本語名称 | E25: VARCHAR | F25: 100 | G25: =VLOOKUP($E25, sql_type[#All], '<SQL> '!$E$3, FALSE ) -> TEXT | J25: Y | M25: {="ITM_"&UPPER(RIGHT(OFFSET(D25,S25,0),LEN(OFFSET(D25,S25,0))-4))&"_"&_xlfn.IFNA(_xlfn.IFS(K25="Y","PKEY",L25="Y","F"&UPPER(B25)),UPPER(B25))} -> ITM_CAT_MAJOR_TITLE_JP | N25: =M25&","&B25&","&OFFSET(G25,0,VLOOKUP($C$5,SQL[#All],2,FALSE) ) &", -- "&D25 -> ITM_CAT_MAJOR_TITLE_JP,title_jp,TEXT, -- 日本語名称 | O25: =LEFT(LEFT("KEY_"&M25&REPT(" ",$O$6),$O$6)&": Final[str] = """&M25&""""&REPT(" ",$O$5),$O$5)&"# "&D25 -> KEY_ITM_CAT_MAJOR_TITLE_JP : Final[str] = "ITM_CAT_MAJOR_TITLE_JP" # 日本語名称 | P25: =$B25 & " " & VLOOKUP($E25, sql_type[#All], '<SQL> '!$E$3, FALSE )& " " & IFERROR( IF($K25="", VLOOKUP(K25, sql_notnull[#All], '<SQL> '!$E$3, FALSE ), VLOOKUP($K25, sql_pk[], '<SQL> '!$E$3, FALSE ) ), "" ) & ", -- " &$D25 -> title_jp TEXT , -- 日本語名称 | S25: -5
B26: =OFFSET( tbl_cat_major[[#Headers],[key_cat_major]], 0, ROWS( $A$24:A26 )-1 ) -> title_en | C26: 英語名称 | D26: 英語名称 | E26: VARCHAR | F26: 100 | G26: =VLOOKUP($E26, sql_type[#All], '<SQL> '!$E$3, FALSE ) -> TEXT | J26: Y | M26: {="ITM_"&UPPER(RIGHT(OFFSET(D26,S26,0),LEN(OFFSET(D26,S26,0))-4))&"_"&_xlfn.IFNA(_xlfn.IFS(K26="Y","PKEY",L26="Y","F"&UPPER(B26)),UPPER(B26))} -> ITM_CAT_MAJOR_TITLE_EN | N26: =M26&","&B26&","&OFFSET(G26,0,VLOOKUP($C$5,SQL[#All],2,FALSE) ) &", -- "&D26 -> ITM_CAT_MAJOR_TITLE_EN,title_en,TEXT, -- 英語名称 | O26: =LEFT(LEFT("KEY_"&M26&REPT(" ",$O$6),$O$6)&": Final[str] = """&M26&""""&REPT(" ",$O$5),$O$5)&"# "&D26 -> KEY_ITM_CAT_MAJOR_TITLE_EN : Final[str] = "ITM_CAT_MAJOR_TITLE_EN" # 英語名称 | P26: =$B26 & " " & VLOOKUP($E26, sql_type[#All], '<SQL> '!$E$3, FALSE )& " " & IFERROR( IF($K26="", VLOOKUP(K26, sql_notnull[#All], '<SQL> '!$E$3, FALSE ), VLOOKUP($K26, sql_pk[], '<SQL> '!$E$3, FALSE ) ), "" ) & ", -- " &$D26 -> title_en TEXT , -- 英語名称 | S26: -6
A27: =B27=B13 -> TRUE | B27: =OFFSET( tbl_cat_major[[#Headers],[key_cat_major]], 0, ROWS( $A$24:A27 )-1 ) -> key_cat_type | C27: 対応する大分類 | D27: 対応する大分類key_cat_type | E27: INT | F27: 4 | G27: =VLOOKUP($E27, sql_type[#All], '<SQL> '!$E$3, FALSE ) -> INTEGER | J27: Y | L27: Y | M27: {="ITM_"&UPPER(RIGHT(OFFSET(D27,S27,0),LEN(OFFSET(D27,S27,0))-4))&"_"&_xlfn.IFNA(_xlfn.IFS(K27="Y","PKEY",L27="Y","F"&UPPER(B27)),UPPER(B27))} -> ITM_CAT_MAJOR_FKEY_CAT_TYPE | N27: =M27&","&B27&","&OFFSET(G27,0,VLOOKUP($C$5,SQL[#All],2,FALSE) ) &", -- "&D27 -> ITM_CAT_MAJOR_FKEY_CAT_TYPE,key_cat_type,INTEGER, -- 対応する大分類key_cat_type | O27: =LEFT(LEFT("KEY_"&M27&REPT(" ",$O$6),$O$6)&": Final[str] = """&M27&""""&REPT(" ",$O$5),$O$5)&"# "&D27 -> KEY_ITM_CAT_MAJOR_FKEY_CAT_TYPE : Final[str] = "ITM_CAT_MAJOR_FKEY_CAT_TYPE" # 対応する大分類key_cat_type | P27: =$B27 & " " & VLOOKUP($E27, sql_type[#All], '<SQL> '!$E$3, FALSE )& " " & IFERROR( IF($K27="", VLOOKUP(K27, sql_notnull[#All], '<SQL> '!$E$3, FALSE ), VLOOKUP($K27, sql_pk[], '<SQL> '!$E$3, FALSE ) ), "" ) & ", -- " &$D27 -> key_cat_type INTEGER , -- 対応する大分類key_cat_type | S27: -7
B28: path | C28: 保存先フォルダのパス | D28: 保存先フォルダのパス | E28: TEXT | G28: =VLOOKUP($E28, sql_type[#All], '<SQL> '!$E$3, FALSE ) -> TEXT | J28: Y | M28: {="ITM_"&UPPER(RIGHT(OFFSET(D28,S28,0),LEN(OFFSET(D28,S28,0))-4))&"_"&_xlfn.IFNA(_xlfn.IFS(K28="Y","PKEY",L28="Y","F"&UPPER(B28)),UPPER(B28))} -> ITM_CAT_MAJOR_PATH | N28: =M28&","&B28&","&OFFSET(G28,0,VLOOKUP($C$5,SQL[#All],2,FALSE) ) &", -- "&D28 -> ITM_CAT_MAJOR_PATH,path,TEXT, -- 保存先フォルダのパス | O28: =LEFT(LEFT("KEY_"&M28&REPT(" ",$O$6),$O$6)&": Final[str] = """&M28&""""&REPT(" ",$O$5),$O$5)&"# "&D28 -> KEY_ITM_CAT_MAJOR_PATH : Final[str] = "ITM_CAT_MAJOR_PATH" # 保存先フォルダのパス | S28: -8
S29: -9
A31: 基準小分類DB
B32: テーブル名 | C32: 物理名 | D32: tbl_cat_sub | N32: =UPPER( D32 ) & "," &D32 & ",," -> TBL_CAT_SUB,tbl_cat_sub,, | O32: =LEFT( LEFT("KEY_"&UPPER(D32)&REPT(" ",$O$6),$O$6) & ": Final[str] = """&UPPER(D32)&"""" & REPT(" ",$O$5),$O$5 ) & "# " &D33 -> KEY_TBL_CAT_SUB : Final[str] = "TBL_CAT_SUB" # 基準小分類テーブル
C33: 論理名 | D33: 基準小分類テーブル
B34: カラム名 | E34: データ型 | J34: 制約 | N34: CREATE
B35: 物理名 | C35: 論理名 | D35: 概要 | E35: Type | F35: Byte | G35: SQLite | H35: SQL Server | I35: MongoDB | J35: NOT_NULL | K35: PK | L35: FK | N35: CSV | P35: SQLite | Q35: SQL Server | R35: MongoDB
B36: =OFFSET( tbl_cat_sub[[#Headers],[key_cat_sub]], 0, ROWS( $A$36:A36 )-1 ) -> key_cat_sub | C36: 小分類キー | D36: 小分類キー | E36: INT | F36: 4 | G36: =VLOOKUP($E36, sql_type[#All], '<SQL> '!$E$3, FALSE ) -> INTEGER | I36: 4 | J36: Y | K36: Y | M36: {="ITM_"&UPPER(RIGHT(OFFSET(D36,S36,0),LEN(OFFSET(D36,S36,0))-4))&"_"&_xlfn.IFNA(_xlfn.IFS(K36="Y","PKEY",L36="Y","F"&UPPER(B36)),UPPER(B36))} -> ITM_CAT_SUB_PKEY | N36: =M36&","&B36&","&OFFSET(G36,0,VLOOKUP($C$5,SQL[#All],2,FALSE) ) &", -- "&D36 -> ITM_CAT_SUB_PKEY,key_cat_sub,INTEGER, -- 小分類キー | O36: =LEFT(LEFT("KEY_"&M36&REPT(" ",$O$6),$O$6)&": Final[str] = """&M36&""""&REPT(" ",$O$5),$O$5)&"# "&D36 -> KEY_ITM_CAT_SUB_PKEY : Final[str] = "ITM_CAT_SUB_PKEY" # 小分類キー | P36: =$B36 & " " & VLOOKUP($E36, sql_type[#All], '<SQL> '!$E$3, FALSE )& " " & IFERROR( IF($K36="", VLOOKUP(K36, sql_notnull[#All], '<SQL> '!$E$3, FALSE ), VLOOKUP($K36, sql_pk[], '<SQL> '!$E$3, FALSE ) ), "" ) & ", -- " &$D36 -> key_cat_sub INTEGER PRIMARY KEY, -- 小分類キー | S36: -4
B37: =OFFSET( tbl_cat_sub[[#Headers],[key_cat_sub]], 0, ROWS( $A$36:A37 )-1 ) -> title_jp | C37: 日本語名称 | D37: 日本語名称 | E37: VARCHAR | F37: 100 | G37: =VLOOKUP($E37, sql_type[#All], '<SQL> '!$E$3, FALSE ) -> TEXT | I37: 100 | J37: Y | M37: {="ITM_"&UPPER(RIGHT(OFFSET(D37,S37,0),LEN(OFFSET(D37,S37,0))-4))&"_"&_xlfn.IFNA(_xlfn.IFS(K37="Y","PKEY",L37="Y","F"&UPPER(B37)),UPPER(B37))} -> ITM_CAT_SUB_TITLE_JP | N37: =M37&","&B37&","&OFFSET(G37,0,VLOOKUP($C$5,SQL[#All],2,FALSE) ) &", -- "&D37 -> ITM_CAT_SUB_TITLE_JP,title_jp,TEXT, -- 日本語名称 | O37: =LEFT(LEFT("KEY_"&M37&REPT(" ",$O$6),$O$6)&": Final[str] = """&M37&""""&REPT(" ",$O$5),$O$5)&"# "&D37 -> KEY_ITM_CAT_SUB_TITLE_JP : Final[str] = "ITM_CAT_SUB_TITLE_JP" # 日本語名称 | P37: =$B37 & " " & VLOOKUP($E37, sql_type[#All], '<SQL> '!$E$3, FALSE )& " " & IFERROR( IF($K37="", VLOOKUP(K37, sql_notnull[#All], '<SQL> '!$E$3, FALSE ), VLOOKUP($K37, sql_pk[], '<SQL> '!$E$3, FALSE ) ), "" ) & ", -- " &$D37 -> title_jp TEXT , -- 日本語名称 | S37: -5
B38: =OFFSET( tbl_cat_sub[[#Headers],[key_cat_sub]], 0, ROWS( $A$36:A38 )-1 ) -> title_en | C38: 英語名称 | D38: 英語名称 | E38: VARCHAR | F38: 100 | G38: =VLOOKUP($E38, sql_type[#All], '<SQL> '!$E$3, FALSE ) -> TEXT | I38: 100 | J38: Y | M38: {="ITM_"&UPPER(RIGHT(OFFSET(D38,S38,0),LEN(OFFSET(D38,S38,0))-4))&"_"&_xlfn.IFNA(_xlfn.IFS(K38="Y","PKEY",L38="Y","F"&UPPER(B38)),UPPER(B38))} -> ITM_CAT_SUB_TITLE_EN | N38: =M38&","&B38&","&OFFSET(G38,0,VLOOKUP($C$5,SQL[#All],2,FALSE) ) &", -- "&D38 -> ITM_CAT_SUB_TITLE_EN,title_en,TEXT, -- 英語名称 | O38: =LEFT(LEFT("KEY_"&M38&REPT(" ",$O$6),$O$6)&": Final[str] = """&M38&""""&REPT(" ",$O$5),$O$5)&"# "&D38 -> KEY_ITM_CAT_SUB_TITLE_EN : Final[str] = "ITM_CAT_SUB_TITLE_EN" # 英語名称 | P38: =$B38 & " " & VLOOKUP($E38, sql_type[#All], '<SQL> '!$E$3, FALSE )& " " & IFERROR( IF($K38="", VLOOKUP(K38, sql_notnull[#All], '<SQL> '!$E$3, FALSE ), VLOOKUP($K38, sql_pk[], '<SQL> '!$E$3, FALSE ) ), "" ) & ", -- " &$D38 -> title_en TEXT , -- 英語名称 | S38: -6
A39: =B39=B24 -> TRUE | B39: =OFFSET( tbl_cat_sub[[#Headers],[key_cat_sub]], 0, ROWS( $A$36:A39 )-1 ) -> key_cat_major | C39: 対応する中分類 | D39: 対応する中分類key_cat_major | E39: INT | F39: 4 | G39: =VLOOKUP($E39, sql_type[#All], '<SQL> '!$E$3, FALSE ) -> INTEGER | I39: 4 | J39: Y | L39: Y | M39: {="ITM_"&UPPER(RIGHT(OFFSET(D39,S39,0),LEN(OFFSET(D39,S39,0))-4))&"_"&_xlfn.IFNA(_xlfn.IFS(K39="Y","PKEY",L39="Y","F"&UPPER(B39)),UPPER(B39))} -> ITM_CAT_SUB_FKEY_CAT_MAJOR | N39: =M39&","&B39&","&OFFSET(G39,0,VLOOKUP($C$5,SQL[#All],2,FALSE) ) &", -- "&D39 -> ITM_CAT_SUB_FKEY_CAT_MAJOR,key_cat_major,INTEGER, -- 対応する中分類key_cat_major | O39: =LEFT(LEFT("KEY_"&M39&REPT(" ",$O$6),$O$6)&": Final[str] = """&M39&""""&REPT(" ",$O$5),$O$5)&"# "&D39 -> KEY_ITM_CAT_SUB_FKEY_CAT_MAJOR : Final[str] = "ITM_CAT_SUB_FKEY_CAT_MAJOR" # 対応する中分類key_cat_major | P39: =$B39 & " " & VLOOKUP($E39, sql_type[#All], '<SQL> '!$E$3, FALSE )& " " & IFERROR( IF($K39="", VLOOKUP(K39, sql_notnull[#All], '<SQL> '!$E$3, FALSE ), VLOOKUP($K39, sql_pk[], '<SQL> '!$E$3, FALSE ) ), "" ) & ", -- " &$D39 -> key_cat_major INTEGER , -- 対応する中分類key_cat_major | S39: -7
B40: path | C40: 保存先フォルダのパス | D40: 保存先フォルダのパス | E40: TEXT | G40: =VLOOKUP($E40, sql_type[#All], '<SQL> '!$E$3, FALSE ) -> TEXT | J40: Y | M40: {="ITM_"&UPPER(RIGHT(OFFSET(D40,S40,0),LEN(OFFSET(D40,S40,0))-4))&"_"&_xlfn.IFNA(_xlfn.IFS(K40="Y","PKEY",L40="Y","F"&UPPER(B40)),UPPER(B40))} -> ITM_CAT_SUB_PATH | N40: =M40&","&B40&","&OFFSET(G40,0,VLOOKUP($C$5,SQL[#All],2,FALSE) ) &", -- "&D40 -> ITM_CAT_SUB_PATH,path,TEXT, -- 保存先フォルダのパス | O40: =LEFT(LEFT("KEY_"&M40&REPT(" ",$O$6),$O$6)&": Final[str] = """&M40&""""&REPT(" ",$O$5),$O$5)&"# "&D40 -> KEY_ITM_CAT_SUB_PATH : Final[str] = "ITM_CAT_SUB_PATH" # 保存先フォルダのパス | P40: =$B40 & " " & VLOOKUP($E40, sql_type[#All], '<SQL> '!$E$3, FALSE )& " " & IFERROR( IF($K40="", VLOOKUP(K40, sql_notnull[#All], '<SQL> '!$E$3, FALSE ), VLOOKUP($K40, sql_pk[], '<SQL> '!$E$3, FALSE ) ), "" ) & ", -- " &$D40 -> path TEXT , -- 保存先フォルダのパス | S40: -8
S41: -9
A44: 状態DB
B45: テーブル名 | C45: 物理名 | D45: tbl_cat_state | N45: =UPPER( D45 ) & "," &D45 & ",," -> TBL_CAT_STATE,tbl_cat_state,, | O45: =LEFT( LEFT("KEY_"&UPPER(D45)&REPT(" ",$O$6),$O$6) & ": Final[str] = """&UPPER(D45)&"""" & REPT(" ",$O$5),$O$5 ) & "# " &D46 -> KEY_TBL_CAT_STATE : Final[str] = "TBL_CAT_STATE" # 基準小分類テーブル
C46: 論理名 | D46: 基準小分類テーブル
B47: カラム名 | E47: データ型 | J47: 制約 | N47: CREATE
B48: 物理名 | C48: 論理名 | D48: 概要 | E48: Type | F48: Byte | G48: SQLite | H48: SQL Server | I48: MongoDB | J48: NOT_NULL | K48: PK | L48: FK | N48: CSV | P48: SQLite | Q48: SQL Server | R48: MongoDB
B49: =OFFSET( tbl_cat_state[[#Headers],[key_cat_state]], 0, ROWS( $A$49:A49 )-1 ) -> key_cat_state | C49: 基準キー | D49: 状態ID（0:作成中 1:制定版 2:廃止） | E49: TINYINT | F49: 1 | G49: =VLOOKUP($E49, sql_type[#All], '<SQL> '!$E$3, FALSE ) -> INTEGER | I49: 1 | J49: Y | K49: Y | M49: {="ITM_"&UPPER(RIGHT(OFFSET(D49,S49,0),LEN(OFFSET(D49,S49,0))-4))&"_"&_xlfn.IFNA(_xlfn.IFS(K49="Y","PKEY",L49="Y","F"&UPPER(B49)),UPPER(B49))} -> ITM_CAT_STATE_PKEY | N49: =M49&","&B49&","&OFFSET(G49,0,VLOOKUP($C$5,SQL[#All],2,FALSE) ) &", -- "&D49 -> ITM_CAT_STATE_PKEY,key_cat_state,INTEGER, -- 状態ID（0:作成中 1:制定版 2:廃止） | O49: =LEFT(LEFT("KEY_"&M49&REPT(" ",$O$6),$O$6)&": Final[str] = """&M49&""""&REPT(" ",$O$5),$O$5)&"# "&D49 -> KEY_ITM_CAT_STATE_PKEY : Final[str] = "ITM_CAT_STATE_PKEY" # 状態ID（0:作成中 1:制定版 2:廃止） | P49: =$B49 & " " & VLOOKUP($E49, sql_type[#All], '<SQL> '!$E$3, FALSE )& " " & IFERROR( IF($K49="", VLOOKUP(K49, sql_notnull[#All], '<SQL> '!$E$3, FALSE ), VLOOKUP($K49, sql_pk[], '<SQL> '!$E$3, FALSE ) ), "" ) & ", -- " &$D49 -> key_cat_state INTEGER PRIMARY KEY, -- 状態ID（0:作成中 1:制定版 2:廃止） | S49: -4
B50: =OFFSET( tbl_cat_state[[#Headers],[key_cat_state]], 0, ROWS( $A$49:A50 )-1 ) -> title_jp | C50: 種類名 | D50: 日本語名称 | E50: VARCHAR | F50: 20 | G50: =VLOOKUP($E50, sql_type[#All], '<SQL> '!$E$3, FALSE ) -> TEXT | I50: 20 | J50: Y | M50: {="ITM_"&UPPER(RIGHT(OFFSET(D50,S50,0),LEN(OFFSET(D50,S50,0))-4))&"_"&_xlfn.IFNA(_xlfn.IFS(K50="Y","PKEY",L50="Y","F"&UPPER(B50)),UPPER(B50))} -> ITM_CAT_STATE_TITLE_JP | N50: =M50&","&B50&","&OFFSET(G50,0,VLOOKUP($C$5,SQL[#All],2,FALSE) ) &", -- "&D50 -> ITM_CAT_STATE_TITLE_JP,title_jp,TEXT, -- 日本語名称 | O50: =LEFT(LEFT("KEY_"&M50&REPT(" ",$O$6),$O$6)&": Final[str] = """&M50&""""&REPT(" ",$O$5),$O$5)&"# "&D50 -> KEY_ITM_CAT_STATE_TITLE_JP : Final[str] = "ITM_CAT_STATE_TITLE_JP" # 日本語名称 | P50: =$B50 & " " & VLOOKUP($E50, sql_type[#All], '<SQL> '!$E$3, FALSE )& " " & IFERROR( IF($K50="", VLOOKUP(K50, sql_notnull[#All], '<SQL> '!$E$3, FALSE ), VLOOKUP($K50, sql_pk[], '<SQL> '!$E$3, FALSE ) ), "" ) & ", -- " &$D50 -> title_jp TEXT , -- 日本語名称 | S50: -5
B51: =OFFSET( tbl_cat_state[[#Headers],[key_cat_state]], 0, ROWS( $A$49:A51 )-1 ) -> title_en | C51: 種類名 | D51: 英語名称 | E51: VARCHAR | F51: 20 | G51: =VLOOKUP($E51, sql_type[#All], '<SQL> '!$E$3, FALSE ) -> TEXT | I51: 20 | J51: Y | M51: {="ITM_"&UPPER(RIGHT(OFFSET(D51,S51,0),LEN(OFFSET(D51,S51,0))-4))&"_"&_xlfn.IFNA(_xlfn.IFS(K51="Y","PKEY",L51="Y","F"&UPPER(B51)),UPPER(B51))} -> ITM_CAT_STATE_TITLE_EN | N51: =M51&","&B51&","&OFFSET(G51,0,VLOOKUP($C$5,SQL[#All],2,FALSE) ) &", -- "&D51 -> ITM_CAT_STATE_TITLE_EN,title_en,TEXT, -- 英語名称 | O51: =LEFT(LEFT("KEY_"&M51&REPT(" ",$O$6),$O$6)&": Final[str] = """&M51&""""&REPT(" ",$O$5),$O$5)&"# "&D51 -> KEY_ITM_CAT_STATE_TITLE_EN : Final[str] = "ITM_CAT_STATE_TITLE_EN" # 英語名称 | P51: =$B51 & " " & VLOOKUP($E51, sql_type[#All], '<SQL> '!$E$3, FALSE )& " " & IFERROR( IF($K51="", VLOOKUP(K51, sql_notnull[#All], '<SQL> '!$E$3, FALSE ), VLOOKUP($K51, sql_pk[], '<SQL> '!$E$3, FALSE ) ), "" ) & ", -- " &$D51 -> title_en TEXT , -- 英語名称 | S51: -6
A54: 基準類DB
B55: テーブル名 | C55: 物理名 | D55: tbl_rules | N55: =UPPER( D55 ) & "," &D55 & ",," -> TBL_RULES,tbl_rules,, | O55: =LEFT( LEFT("KEY_"&UPPER(D55)&REPT(" ",$O$6),$O$6) & ": Final[str] = """&UPPER(D55)&"""" & REPT(" ",$O$5),$O$5 ) & "# " &D56 -> KEY_TBL_RULES : Final[str] = "TBL_RULES" # 基準類テーブル
C56: 論理名 | D56: 基準類テーブル
B57: カラム名 | E57: データ型 | J57: 制約 | N57: CREATE
B58: 物理名 | C58: 論理名 | D58: 概要 | E58: Type | F58: Byte | G58: SQLite | H58: SQL Server | I58: MongoDB | J58: NOT_NULL | K58: PK | L58: FK | N58: CSV | P58: SQLite | Q58: SQL Server | R58: MongoDB
B59: =OFFSET( tbl_rules[[#Headers],[key_rule]], 0, ROWS( $A$59:A59 )-1 ) -> key_rule | C59: 基準キー | D59: ルール通し番号 | E59: INT | F59: 4 | G59: =VLOOKUP($E59, sql_type[#All], '<SQL> '!$E$3, FALSE ) -> INTEGER | I59: 4 | J59: Y | K59: Y | M59: {="ITM_"&UPPER(RIGHT(OFFSET(D59,S59,0),LEN(OFFSET(D59,S59,0))-4))&"_"&_xlfn.IFNA(_xlfn.IFS(K59="Y","PKEY",L59="Y","F"&UPPER(B59)),UPPER(B59))} -> ITM_RULES_PKEY | N59: =M59&","&B59&","&OFFSET(G59,0,VLOOKUP($C$5,SQL[#All],2,FALSE) ) &", -- "&D59 -> ITM_RULES_PKEY,key_rule,INTEGER, -- ルール通し番号 | O59: =LEFT(LEFT("KEY_"&M59&REPT(" ",$O$6),$O$6)&": Final[str] = """&M59&""""&REPT(" ",$O$5),$O$5)&"# "&D59 -> KEY_ITM_RULES_PKEY : Final[str] = "ITM_RULES_PKEY" # ルール通し番号 | P59: =$B59 & " " & VLOOKUP($E59, sql_type[#All], '<SQL> '!$E$3, FALSE )& " " & IFERROR( IF($K59="", VLOOKUP(K59, sql_notnull[#All], '<SQL> '!$E$3, FALSE ), VLOOKUP($K59, sql_pk[], '<SQL> '!$E$3, FALSE ) ), "" ) & ", -- " &$D59 -> key_rule INTEGER PRIMARY KEY, -- ルール通し番号 | S59: -4
B60: =OFFSET( tbl_rules[[#Headers],[key_rule]], 0, ROWS( $A$59:A60 )-1 ) -> id_rule | C60: 文書ID | D60: 文書ID | E60: VARCHAR | F60: 100 | G60: =VLOOKUP($E60, sql_type[#All], '<SQL> '!$E$3, FALSE ) -> TEXT | I60: 100 | J60: Y | M60: {="ITM_"&UPPER(RIGHT(OFFSET(D60,S60,0),LEN(OFFSET(D60,S60,0))-4))&"_"&_xlfn.IFNA(_xlfn.IFS(K60="Y","PKEY",L60="Y","F"&UPPER(B60)),UPPER(B60))} -> ITM_RULES_ID_RULE | N60: =M60&","&B60&","&OFFSET(G60,0,VLOOKUP($C$5,SQL[#All],2,FALSE) ) &", -- "&D60 -> ITM_RULES_ID_RULE,id_rule,TEXT, -- 文書ID | O60: =LEFT(LEFT("KEY_"&M60&REPT(" ",$O$6),$O$6)&": Final[str] = """&M60&""""&REPT(" ",$O$5),$O$5)&"# "&D60 -> KEY_ITM_RULES_ID_RULE : Final[str] = "ITM_RULES_ID_RULE" # 文書ID | S60: -5
B61: =OFFSET( tbl_rules[[#Headers],[key_rule]], 0, ROWS( $A$59:A61 )-1 ) -> name_rule | C61: 文書名 | D61: 文書名 | E61: VARCHAR | F61: 200 | G61: =VLOOKUP($E61, sql_type[#All], '<SQL> '!$E$3, FALSE ) -> TEXT | I61: 200 | J61: Y | M61: {="ITM_"&UPPER(RIGHT(OFFSET(D61,S61,0),LEN(OFFSET(D61,S61,0))-4))&"_"&_xlfn.IFNA(_xlfn.IFS(K61="Y","PKEY",L61="Y","F"&UPPER(B61)),UPPER(B61))} -> ITM_RULES_NAME_RULE | N61: =M61&","&B61&","&OFFSET(G61,0,VLOOKUP($C$5,SQL[#All],2,FALSE) ) &", -- "&D61 -> ITM_RULES_NAME_RULE,name_rule,TEXT, -- 文書名 | O61: =LEFT(LEFT("KEY_"&M61&REPT(" ",$O$6),$O$6)&": Final[str] = """&M61&""""&REPT(" ",$O$5),$O$5)&"# "&D61 -> KEY_ITM_RULES_NAME_RULE : Final[str] = "ITM_RULES_NAME_RULE" # 文書名 | S61: -6
A62: =B62=B36 -> TRUE | B62: =OFFSET( tbl_rules[[#Headers],[key_rule]], 0, ROWS( $A$59:A62 )-1 ) -> key_cat_sub | C62: 小分類キー | D62: 小分類キー | E62: INT | F62: 4 | G62: =VLOOKUP($E62, sql_type[#All], '<SQL> '!$E$3, FALSE ) -> INTEGER | I62: 4 | J62: Y | L62: Y | M62: {="ITM_"&UPPER(RIGHT(OFFSET(D62,S62,0),LEN(OFFSET(D62,S62,0))-4))&"_"&_xlfn.IFNA(_xlfn.IFS(K62="Y","PKEY",L62="Y","F"&UPPER(B62)),UPPER(B62))} -> ITM_RULES_FKEY_CAT_SUB | N62: =M62&","&B62&","&OFFSET(G62,0,VLOOKUP($C$5,SQL[#All],2,FALSE) ) &", -- "&D62 -> ITM_RULES_FKEY_CAT_SUB,key_cat_sub,INTEGER, -- 小分類キー | O62: =LEFT(LEFT("KEY_"&M62&REPT(" ",$O$6),$O$6)&": Final[str] = """&M62&""""&REPT(" ",$O$5),$O$5)&"# "&D62 -> KEY_ITM_RULES_FKEY_CAT_SUB : Final[str] = "ITM_RULES_FKEY_CAT_SUB" # 小分類キー | S62: -7
B63: =OFFSET( tbl_rules[[#Headers],[key_rule]], 0, ROWS( $A$59:A63 )-1 ) -> link | C63: 元文書へのURL | D63: 元文書へのURL | E63: TEXT | G63: =VLOOKUP($E63, sql_type[#All], '<SQL> '!$E$3, FALSE ) -> TEXT | J63: Y | M63: {="ITM_"&UPPER(RIGHT(OFFSET(D63,S63,0),LEN(OFFSET(D63,S63,0))-4))&"_"&_xlfn.IFNA(_xlfn.IFS(K63="Y","PKEY",L63="Y","F"&UPPER(B63)),UPPER(B63))} -> ITM_RULES_LINK | N63: =M63&","&B63&","&OFFSET(G63,0,VLOOKUP($C$5,SQL[#All],2,FALSE) ) &", -- "&D63 -> ITM_RULES_LINK,link,TEXT, -- 元文書へのURL | O63: =LEFT(LEFT("KEY_"&M63&REPT(" ",$O$6),$O$6)&": Final[str] = """&M63&""""&REPT(" ",$O$5),$O$5)&"# "&D63 -> KEY_ITM_RULES_LINK : Final[str] = "ITM_RULES_LINK" # 元文書へのURL | S63: -8
A64: =B64=B49 -> TRUE | B64: =OFFSET( tbl_rules[[#Headers],[key_rule]], 0, ROWS( $A$59:A64 )-1 ) -> key_cat_state | C64: 状態ID | D64: 状態ID | E64: TINYINT | F64: 1 | G64: =VLOOKUP($E64, sql_type[#All], '<SQL> '!$E$3, FALSE ) -> INTEGER | I64: 1 | J64: Y | L64: Y | M64: {="ITM_"&UPPER(RIGHT(OFFSET(D64,S64,0),LEN(OFFSET(D64,S64,0))-4))&"_"&_xlfn.IFNA(_xlfn.IFS(K64="Y","PKEY",L64="Y","F"&UPPER(B64)),UPPER(B64))} -> ITM_RULES_FKEY_CAT_STATE | N64: =M64&","&B64&","&OFFSET(G64,0,VLOOKUP($C$5,SQL[#All],2,FALSE) ) &", -- "&D64 -> ITM_RULES_FKEY_CAT_STATE,key_cat_state,INTEGER, -- 状態ID | O64: =LEFT(LEFT("KEY_"&M64&REPT(" ",$O$6),$O$6)&": Final[str] = """&M64&""""&REPT(" ",$O$5),$O$5)&"# "&D64 -> KEY_ITM_RULES_FKEY_CAT_STATE : Final[str] = "ITM_RULES_FKEY_CAT_STATE" # 状態ID | S64: -9
B65: =OFFSET( tbl_rules[[#Headers],[key_rule]], 0, ROWS( $A$59:A65 )-1 ) -> created_date | C65: 制定日など | D65: 制定日など | E65: DATETIME | F65: 8 | G65: =VLOOKUP($E65, sql_type[#All], '<SQL> '!$E$3, FALSE ) -> TEXT | I65: 8 | J65: N | M65: {="ITM_"&UPPER(RIGHT(OFFSET(D65,S65,0),LEN(OFFSET(D65,S65,0))-4))&"_"&_xlfn.IFNA(_xlfn.IFS(K65="Y","PKEY",L65="Y","F"&UPPER(B65)),UPPER(B65))} -> ITM_RULES_CREATED_DATE | N65: =M65&","&B65&","&OFFSET(G65,0,VLOOKUP($C$5,SQL[#All],2,FALSE) ) &", -- "&D65 -> ITM_RULES_CREATED_DATE,created_date,TEXT, -- 制定日など | O65: =LEFT(LEFT("KEY_"&M65&REPT(" ",$O$6),$O$6)&": Final[str] = """&M65&""""&REPT(" ",$O$5),$O$5)&"# "&D65 -> KEY_ITM_RULES_CREATED_DATE : Final[str] = "ITM_RULES_CREATED_DATE" # 制定日など | S65: -10
B66: =OFFSET( tbl_rules[[#Headers],[key_rule]], 0, ROWS( $A$59:A66 )-1 ) -> update_date | C66: 改訂日など | D66: 改訂日など | E66: DATETIME | F66: 8 | G66: =VLOOKUP($E66, sql_type[#All], '<SQL> '!$E$3, FALSE ) -> TEXT | I66: 8 | J66: N | M66: {="ITM_"&UPPER(RIGHT(OFFSET(D66,S66,0),LEN(OFFSET(D66,S66,0))-4))&"_"&_xlfn.IFNA(_xlfn.IFS(K66="Y","PKEY",L66="Y","F"&UPPER(B66)),UPPER(B66))} -> ITM_RULES_UPDATE_DATE | N66: =M66&","&B66&","&OFFSET(G66,0,VLOOKUP($C$5,SQL[#All],2,FALSE) ) &", -- "&D66 -> ITM_RULES_UPDATE_DATE,update_date,TEXT, -- 改訂日など | O66: =LEFT(LEFT("KEY_"&M66&REPT(" ",$O$6),$O$6)&": Final[str] = """&M66&""""&REPT(" ",$O$5),$O$5)&"# "&D66 -> KEY_ITM_RULES_UPDATE_DATE : Final[str] = "ITM_RULES_UPDATE_DATE" # 改訂日など | S66: -11
S67: -12
A69: 要件カテゴリ
B70: テーブル名 | C70: 物理名 | D70: tbl_cat_request | N70: =UPPER( D70 ) & "," &D70 & ",," -> TBL_CAT_REQUEST,tbl_cat_request,, | O70: =LEFT( LEFT("KEY_"&UPPER(D70)&REPT(" ",$O$6),$O$6) & ": Final[str] = """&UPPER(D70)&"""" & REPT(" ",$O$5),$O$5 ) & "# " &D71 -> KEY_TBL_CAT_REQUEST : Final[str] = "TBL_CAT_REQUEST" # 設計領域テーブル
C71: 論理名 | D71: 設計領域テーブル
B72: カラム名 | E72: データ型 | J72: 制約 | N72: CREATE
B73: 物理名 | C73: 論理名 | D73: 概要 | E73: Type | F73: Byte | G73: SQLite | H73: SQL Server | I73: MongoDB | J73: NOT_NULL | K73: PK | L73: FK | N73: CSV | P73: SQLite | Q73: SQL Server | R73: MongoDB
B74: =OFFSET( tbl_cat_request[[#Headers],[key_cat_request]], 0, ROWS( $A$74:A74 )-1 ) -> key_cat_request | C74: 設計領域ID | D74: 設計領域ID | E74: INT | F74: 4 | G74: =VLOOKUP($E74, sql_type[#All], '<SQL> '!$E$3, FALSE ) -> INTEGER | J74: Y | K74: Y | M74: {="ITM_"&UPPER(RIGHT(OFFSET(D74,S74,0),LEN(OFFSET(D74,S74,0))-4))&"_"&_xlfn.IFNA(_xlfn.IFS(K74="Y","PKEY",L74="Y","F"&UPPER(B74)),UPPER(B74))} -> ITM_CAT_REQUEST_PKEY | N74: =M74&","&B74&","&OFFSET(G74,0,VLOOKUP($C$5,SQL[#All],2,FALSE) ) &", -- "&D74 -> ITM_CAT_REQUEST_PKEY,key_cat_request,INTEGER, -- 設計領域ID | O74: =LEFT(LEFT("KEY_"&M74&REPT(" ",$O$6),$O$6)&": Final[str] = """&M74&""""&REPT(" ",$O$5),$O$5)&"# "&D74 -> KEY_ITM_CAT_REQUEST_PKEY : Final[str] = "ITM_CAT_REQUEST_PKEY" # 設計領域ID | P74: =$B74 & " " & VLOOKUP($E74, sql_type[#All], '<SQL> '!$E$3, FALSE )& " " & IFERROR( IF($K74="", VLOOKUP(K74, sql_notnull[#All], '<SQL> '!$E$3, FALSE ), VLOOKUP($K74, sql_pk[], '<SQL> '!$E$3, FALSE ) ), "" ) & ", -- " &$D74 -> key_cat_request INTEGER PRIMARY KEY, -- 設計領域ID | S74: -4
B75: =OFFSET( tbl_cat_request[[#Headers],[key_cat_request]], 0, ROWS( $A$74:A75 )-1 ) -> title_jp | C75: 日本語名称 | D75: 日本語名称 | E75: VARCHAR | F75: 20 | G75: =VLOOKUP($E75, sql_type[#All], '<SQL> '!$E$3, FALSE ) -> TEXT | J75: Y | M75: {="ITM_"&UPPER(RIGHT(OFFSET(D75,S75,0),LEN(OFFSET(D75,S75,0))-4))&"_"&_xlfn.IFNA(_xlfn.IFS(K75="Y","PKEY",L75="Y","F"&UPPER(B75)),UPPER(B75))} -> ITM_CAT_REQUEST_TITLE_JP | N75: =M75&","&B75&","&OFFSET(G75,0,VLOOKUP($C$5,SQL[#All],2,FALSE) ) &", -- "&D75 -> ITM_CAT_REQUEST_TITLE_JP,title_jp,TEXT, -- 日本語名称 | O75: =LEFT(LEFT("KEY_"&M75&REPT(" ",$O$6),$O$6)&": Final[str] = """&M75&""""&REPT(" ",$O$5),$O$5)&"# "&D75 -> KEY_ITM_CAT_REQUEST_TITLE_JP : Final[str] = "ITM_CAT_REQUEST_TITLE_JP" # 日本語名称 | S75: -5
B76: =OFFSET( tbl_cat_request[[#Headers],[key_cat_request]], 0, ROWS( $A$74:A76 )-1 ) -> title_en | C76: 英語名称 | D76: 英語名称 | E76: VARCHAR | F76: 20 | G76: =VLOOKUP($E76, sql_type[#All], '<SQL> '!$E$3, FALSE ) -> TEXT | J76: N | M76: {="ITM_"&UPPER(RIGHT(OFFSET(D76,S76,0),LEN(OFFSET(D76,S76,0))-4))&"_"&_xlfn.IFNA(_xlfn.IFS(K76="Y","PKEY",L76="Y","F"&UPPER(B76)),UPPER(B76))} -> ITM_CAT_REQUEST_TITLE_EN | N76: =M76&","&B76&","&OFFSET(G76,0,VLOOKUP($C$5,SQL[#All],2,FALSE) ) &", -- "&D76 -> ITM_CAT_REQUEST_TITLE_EN,title_en,TEXT, -- 英語名称 | O76: =LEFT(LEFT("KEY_"&M76&REPT(" ",$O$6),$O$6)&": Final[str] = """&M76&""""&REPT(" ",$O$5),$O$5)&"# "&D76 -> KEY_ITM_CAT_REQUEST_TITLE_EN : Final[str] = "ITM_CAT_REQUEST_TITLE_EN" # 英語名称 | S76: -6
B77: =OFFSET( tbl_cat_request[[#Headers],[key_cat_request]], 0, ROWS( $A$74:A77 )-1 ) -> key_cat_req_type | C77: 英語名称 | D77: 要件種類ID | E77: VARCHAR | F77: 20 | G77: =VLOOKUP($E77, sql_type[#All], '<SQL> '!$E$3, FALSE ) -> TEXT | J77: N | M77: {="ITM_"&UPPER(RIGHT(OFFSET(D77,S77,0),LEN(OFFSET(D77,S77,0))-4))&"_"&_xlfn.IFNA(_xlfn.IFS(K77="Y","PKEY",L77="Y","F"&UPPER(B77)),UPPER(B77))} -> ITM_CAT_REQUEST_KEY_CAT_REQ_TYPE | N77: =M77&","&B77&","&OFFSET(G77,0,VLOOKUP($C$5,SQL[#All],2,FALSE) ) &", -- "&D77 -> ITM_CAT_REQUEST_KEY_CAT_REQ_TYPE,key_cat_req_type,TEXT, -- 要件種類ID | O77: =LEFT(LEFT("KEY_"&M77&REPT(" ",$O$6),$O$6)&": Final[str] = """&M77&""""&REPT(" ",$O$5),$O$5)&"# "&D77 -> KEY_ITM_CAT_REQUEST_KEY_CAT_REQ_TYPE : Final[str] = "ITM_CAT_REQUEST_KEY_CAT_REQ_TYPE" # 要件種類ID | S77: -7
B78: =OFFSET( tbl_cat_request[[#Headers],[key_cat_request]], 0, ROWS( $A$74:A78 )-1 ) -> req_type | C78: 英語名称 | D78: 要件種類 | E78: VARCHAR | F78: 20 | G78: =VLOOKUP($E78, sql_type[#All], '<SQL> '!$E$3, FALSE ) -> TEXT | J78: N | M78: {="ITM_"&UPPER(RIGHT(OFFSET(D78,S78,0),LEN(OFFSET(D78,S78,0))-4))&"_"&_xlfn.IFNA(_xlfn.IFS(K78="Y","PKEY",L78="Y","F"&UPPER(B78)),UPPER(B78))} -> ITM_CAT_REQUEST_REQ_TYPE | N78: =M78&","&B78&","&OFFSET(G78,0,VLOOKUP($C$5,SQL[#All],2,FALSE) ) &", -- "&D78 -> ITM_CAT_REQUEST_REQ_TYPE,req_type,TEXT, -- 要件種類 | O78: =LEFT(LEFT("KEY_"&M78&REPT(" ",$O$6),$O$6)&": Final[str] = """&M78&""""&REPT(" ",$O$5),$O$5)&"# "&D78 -> KEY_ITM_CAT_REQUEST_REQ_TYPE : Final[str] = "ITM_CAT_REQUEST_REQ_TYPE" # 要件種類 | S78: -8
S79: -9
S80: -10
A82: 対応フェーズ
B83: テーブル名 | C83: 物理名 | D83: tbl_cat_phase | N83: =UPPER( D83 ) & "," &D83 & ",," -> TBL_CAT_PHASE,tbl_cat_phase,, | O83: =LEFT( LEFT("KEY_"&UPPER(D83)&REPT(" ",$O$6),$O$6) & ": Final[str] = """&UPPER(D83)&"""" & REPT(" ",$O$5),$O$5 ) & "# " &D84 -> KEY_TBL_CAT_PHASE : Final[str] = "TBL_CAT_PHASE" # 設計領域テーブル
C84: 論理名 | D84: 設計領域テーブル
B85: カラム名 | E85: データ型 | J85: 制約 | N85: CREATE
B86: 物理名 | C86: 論理名 | D86: 概要 | E86: Type | F86: Byte | G86: SQLite | H86: SQL Server | I86: MongoDB | J86: NOT_NULL | K86: PK | L86: FK | N86: CSV | P86: SQLite | Q86: SQL Server | R86: MongoDB
B87: =OFFSET( tbl_cat_phase[[#Headers],[key_cat_phase]], 0, ROWS( $A$87:A87 )-1 ) -> key_cat_phase | C87: 設計領域ID | D87: 設計領域ID | E87: INT | G87: =VLOOKUP($E87, sql_type[#All], '<SQL> '!$E$3, FALSE ) -> INTEGER | J87: Y | K87: Y | M87: {="ITM_"&UPPER(RIGHT(OFFSET(D87,S87,0),LEN(OFFSET(D87,S87,0))-4))&"_"&_xlfn.IFNA(_xlfn.IFS(K87="Y","PKEY",L87="Y","F"&UPPER(B87)),UPPER(B87))} -> ITM_CAT_PHASE_PKEY | N87: =M87&","&B87&","&OFFSET(G87,0,VLOOKUP($C$5,SQL[#All],2,FALSE) ) &", -- "&D87 -> ITM_CAT_PHASE_PKEY,key_cat_phase,INTEGER, -- 設計領域ID | O87: =LEFT(LEFT("KEY_"&M87&REPT(" ",$O$6),$O$6)&": Final[str] = """&M87&""""&REPT(" ",$O$5),$O$5)&"# "&D87 -> KEY_ITM_CAT_PHASE_PKEY : Final[str] = "ITM_CAT_PHASE_PKEY" # 設計領域ID | P87: =$B87 & " " & VLOOKUP($E87, sql_type[#All], '<SQL> '!$E$3, FALSE )& " " & IFERROR( IF($K87="", VLOOKUP(K87, sql_notnull[#All], '<SQL> '!$E$3, FALSE ), VLOOKUP($K87, sql_pk[], '<SQL> '!$E$3, FALSE ) ), "" ) & ", -- " &$D87 -> key_cat_phase INTEGER PRIMARY KEY, -- 設計領域ID | S87: -4
B88: =OFFSET( tbl_cat_phase[[#Headers],[key_cat_phase]], 0, ROWS( $A$87:A88 )-1 ) -> title_jp | C88: 日本語名称 | D88: 日本語名称 | E88: VARCHAR | G88: =VLOOKUP($E88, sql_type[#All], '<SQL> '!$E$3, FALSE ) -> TEXT | J88: Y | M88: {="ITM_"&UPPER(RIGHT(OFFSET(D88,S88,0),LEN(OFFSET(D88,S88,0))-4))&"_"&_xlfn.IFNA(_xlfn.IFS(K88="Y","PKEY",L88="Y","F"&UPPER(B88)),UPPER(B88))} -> ITM_CAT_PHASE_TITLE_JP | N88: =M88&","&B88&","&OFFSET(G88,0,VLOOKUP($C$5,SQL[#All],2,FALSE) ) &", -- "&D88 -> ITM_CAT_PHASE_TITLE_JP,title_jp,TEXT, -- 日本語名称 | O88: =LEFT(LEFT("KEY_"&M88&REPT(" ",$O$6),$O$6)&": Final[str] = """&M88&""""&REPT(" ",$O$5),$O$5)&"# "&D88 -> KEY_ITM_CAT_PHASE_TITLE_JP : Final[str] = "ITM_CAT_PHASE_TITLE_JP" # 日本語名称 | S88: -5
B89: =OFFSET( tbl_cat_phase[[#Headers],[key_cat_phase]], 0, ROWS( $A$87:A89 )-1 ) -> title_en | C89: 英語名称 | D89: 英語名称 | E89: VARCHAR | G89: =VLOOKUP($E89, sql_type[#All], '<SQL> '!$E$3, FALSE ) -> TEXT | J89: N | M89: {="ITM_"&UPPER(RIGHT(OFFSET(D89,S89,0),LEN(OFFSET(D89,S89,0))-4))&"_"&_xlfn.IFNA(_xlfn.IFS(K89="Y","PKEY",L89="Y","F"&UPPER(B89)),UPPER(B89))} -> ITM_CAT_PHASE_TITLE_EN | N89: =M89&","&B89&","&OFFSET(G89,0,VLOOKUP($C$5,SQL[#All],2,FALSE) ) &", -- "&D89 -> ITM_CAT_PHASE_TITLE_EN,title_en,TEXT, -- 英語名称 | O89: =LEFT(LEFT("KEY_"&M89&REPT(" ",$O$6),$O$6)&": Final[str] = """&M89&""""&REPT(" ",$O$5),$O$5)&"# "&D89 -> KEY_ITM_CAT_PHASE_TITLE_EN : Final[str] = "ITM_CAT_PHASE_TITLE_EN" # 英語名称 | S89: -6
S90: -7
A92: 販売地域
B93: テーブル名 | C93: 物理名 | D93: tbl_scp_sales_region | N93: =UPPER( D93 ) & "," &D93 & ",," -> TBL_SCP_SALES_REGION,tbl_scp_sales_region,, | O93: =LEFT( LEFT("KEY_"&UPPER(D93)&REPT(" ",$O$6),$O$6) & ": Final[str] = """&UPPER(D93)&"""" & REPT(" ",$O$5),$O$5 ) & "# " &D94 -> KEY_TBL_SCP_SALES_REGION : Final[str] = "TBL_SCP_SALES_REGION" # 要件類テーブル
C94: 論理名 | D94: 要件類テーブル
B95: カラム名 | E95: データ型 | J95: 制約 | N95: CREATE
B96: 物理名 | C96: 論理名 | D96: 概要 | E96: Type | F96: Byte | G96: SQLite | H96: SQL Server | I96: MongoDB | J96: NOT_NULL | K96: PK | L96: FK | N96: CSV | P96: SQLite | Q96: SQL Server | R96: MongoDB
B97: =OFFSET( tbl_scp_sales_region[[#Headers],[key_scp_sales_region]], 0, ROWS( $A$97:A97 )-1 ) -> key_scp_sales_region | C97: 販売地域ID | D97: 販売地域ID | E97: INT | F97: 4 | G97: =VLOOKUP($E97, sql_type[#All], '<SQL> '!$E$3, FALSE ) -> INTEGER | J97: Y | K97: Y | M97: {="ITM_"&UPPER(RIGHT(OFFSET(D97,S97,0),LEN(OFFSET(D97,S97,0))-4))&"_"&_xlfn.IFNA(_xlfn.IFS(K97="Y","PKEY",L97="Y","F"&UPPER(B97)),UPPER(B97))} -> ITM_SCP_SALES_REGION_PKEY | N97: =M97&","&B97&","&OFFSET(G97,0,VLOOKUP($C$5,SQL[#All],2,FALSE) ) &", -- "&D97 -> ITM_SCP_SALES_REGION_PKEY,key_scp_sales_region,INTEGER, -- 販売地域ID | O97: =LEFT(LEFT("KEY_"&M97&REPT(" ",$O$6),$O$6)&": Final[str] = """&M97&""""&REPT(" ",$O$5),$O$5)&"# "&D97 -> KEY_ITM_SCP_SALES_REGION_PKEY : Final[str] = "ITM_SCP_SALES_REGION_PKEY" # 販売地域ID | P97: =$B97 & " " & VLOOKUP($E97, sql_type[#All], '<SQL> '!$E$3, FALSE )& " " & IFERROR( IF($K97="", VLOOKUP(K97, sql_notnull[#All], '<SQL> '!$E$3, FALSE ), VLOOKUP($K97, sql_pk[], '<SQL> '!$E$3, FALSE ) ), "" ) & ", -- " &$D97 -> key_scp_sales_region INTEGER PRIMARY KEY, -- 販売地域ID | S97: -4
B98: =OFFSET( tbl_scp_sales_region[[#Headers],[key_scp_sales_region]], 0, ROWS( $A$97:A98 )-1 ) -> title_jp | C98: 日本語名称 | D98: 日本語名称 | E98: VARCHAR | F98: 20 | G98: =VLOOKUP($E98, sql_type[#All], '<SQL> '!$E$3, FALSE ) -> TEXT | J98: Y | M98: {="ITM_"&UPPER(RIGHT(OFFSET(D98,S98,0),LEN(OFFSET(D98,S98,0))-4))&"_"&_xlfn.IFNA(_xlfn.IFS(K98="Y","PKEY",L98="Y","F"&UPPER(B98)),UPPER(B98))} -> ITM_SCP_SALES_REGION_TITLE_JP | N98: =M98&","&B98&","&OFFSET(G98,0,VLOOKUP($C$5,SQL[#All],2,FALSE) ) &", -- "&D98 -> ITM_SCP_SALES_REGION_TITLE_JP,title_jp,TEXT, -- 日本語名称 | O98: =LEFT(LEFT("KEY_"&M98&REPT(" ",$O$6),$O$6)&": Final[str] = """&M98&""""&REPT(" ",$O$5),$O$5)&"# "&D98 -> KEY_ITM_SCP_SALES_REGION_TITLE_JP : Final[str] = "ITM_SCP_SALES_REGION_TITLE_JP" # 日本語名称 | S98: -5
B99: =OFFSET( tbl_scp_sales_region[[#Headers],[key_scp_sales_region]], 0, ROWS( $A$97:A99 )-1 ) -> title_en | C99: 英語名称 | D99: 英語名称 | E99: VARCHAR | F99: 20 | G99: =VLOOKUP($E99, sql_type[#All], '<SQL> '!$E$3, FALSE ) -> TEXT | J99: N | M99: {="ITM_"&UPPER(RIGHT(OFFSET(D99,S99,0),LEN(OFFSET(D99,S99,0))-4))&"_"&_xlfn.IFNA(_xlfn.IFS(K99="Y","PKEY",L99="Y","F"&UPPER(B99)),UPPER(B99))} -> ITM_SCP_SALES_REGION_TITLE_EN | N99: =M99&","&B99&","&OFFSET(G99,0,VLOOKUP($C$5,SQL[#All],2,FALSE) ) &", -- "&D99 -> ITM_SCP_SALES_REGION_TITLE_EN,title_en,TEXT, -- 英語名称 | O99: =LEFT(LEFT("KEY_"&M99&REPT(" ",$O$6),$O$6)&": Final[str] = """&M99&""""&REPT(" ",$O$5),$O$5)&"# "&D99 -> KEY_ITM_SCP_SALES_REGION_TITLE_EN : Final[str] = "ITM_SCP_SALES_REGION_TITLE_EN" # 英語名称 | S99: -6
B100: =OFFSET( tbl_scp_sales_region[[#Headers],[key_scp_sales_region]], 0, ROWS( $A$97:A100 )-1 ) -> country_code_2 | C100: 国コード２桁 | D100: 国コード２桁 ISO 3166-1 alpha-2 | E100: VARCHAR | F100: 4 | G100: =VLOOKUP($E100, sql_type[#All], '<SQL> '!$E$3, FALSE ) -> TEXT | J100: N | M100: {="ITM_"&UPPER(RIGHT(OFFSET(D100,S100,0),LEN(OFFSET(D100,S100,0))-4))&"_"&_xlfn.IFNA(_xlfn.IFS(K100="Y","PKEY",L100="Y","F"&UPPER(B100)),UPPER(B100))} -> ITM_SCP_SALES_REGION_COUNTRY_CODE_2 | N100: =M100&","&B100&","&OFFSET(G100,0,VLOOKUP($C$5,SQL[#All],2,FALSE) ) &", -- "&D100 -> ITM_SCP_SALES_REGION_COUNTRY_CODE_2,country_code_2,TEXT, -- 国コード２桁 ISO 3166-1 alpha-2 | O100: =LEFT(LEFT("KEY_"&M100&REPT(" ",$O$6),$O$6)&": Final[str] = """&M100&""""&REPT(" ",$O$5),$O$5)&"# "&D100 -> KEY_ITM_SCP_SALES_REGION_COUNTRY_CODE_2 : Final[str] = "ITM_SCP_SALES_REGION_COUNTRY_CODE_2" # 国コード２桁 ISO 3166-1 alpha-2 | S100: -7
B101: =OFFSET( tbl_scp_sales_region[[#Headers],[key_scp_sales_region]], 0, ROWS( $A$97:A101 )-1 ) -> country_code_3 | C101: 国コード３桁 | D101: 国コード３桁 ISO 3166-1 alpha-3 | E101: VARCHAR | F101: 6 | G101: =VLOOKUP($E101, sql_type[#All], '<SQL> '!$E$3, FALSE ) -> TEXT | J101: N | M101: {="ITM_"&UPPER(RIGHT(OFFSET(D101,S101,0),LEN(OFFSET(D101,S101,0))-4))&"_"&_xlfn.IFNA(_xlfn.IFS(K101="Y","PKEY",L101="Y","F"&UPPER(B101)),UPPER(B101))} -> ITM_SCP_SALES_REGION_COUNTRY_CODE_3 | N101: =M101&","&B101&","&OFFSET(G101,0,VLOOKUP($C$5,SQL[#All],2,FALSE) ) &", -- "&D101 -> ITM_SCP_SALES_REGION_COUNTRY_CODE_3,country_code_3,TEXT, -- 国コード３桁 ISO 3166-1 alpha-3 | O101: =LEFT(LEFT("KEY_"&M101&REPT(" ",$O$6),$O$6)&": Final[str] = """&M101&""""&REPT(" ",$O$5),$O$5)&"# "&D101 -> KEY_ITM_SCP_SALES_REGION_COUNTRY_CODE_3 : Final[str] = "ITM_SCP_SALES_REGION_COUNTRY_CODE_3" # 国コード３桁 ISO 3166-1 alpha-3 | S101: -8
S102: -9
A104: 製品ジャンル
B105: テーブル名 | C105: 物理名 | D105: tbl_scp_product_genre | N105: =UPPER( D105 ) & "," &D105 & ",," -> TBL_SCP_PRODUCT_GENRE,tbl_scp_product_genre,, | O105: =LEFT( LEFT("KEY_"&UPPER(D105)&REPT(" ",$O$6),$O$6) & ": Final[str] = """&UPPER(D105)&"""" & REPT(" ",$O$5),$O$5 ) & "# " &D106 -> KEY_TBL_SCP_PRODUCT_GENRE : Final[str] = "TBL_SCP_PRODUCT_GENRE" # 販売地域テーブル
C106: 論理名 | D106: 販売地域テーブル
B107: カラム名 | E107: データ型 | J107: 制約 | N107: CREATE
B108: 物理名 | C108: 論理名 | D108: 概要 | E108: Type | F108: Byte | G108: SQLite | H108: SQL Server | I108: MongoDB | J108: NOT_NULL | K108: PK | L108: FK | N108: CSV | P108: SQLite | Q108: SQL Server | R108: MongoDB
B109: =OFFSET( tbl_scp_product_genre[[#Headers],[key_scp_product_genre]], 0, ROWS( $A$109:A109 )-1 ) -> key_scp_product_genre | C109: 製品ジャンル | D109: 製品ジャンルID | E109: INT | F109: 4 | G109: =VLOOKUP($E109, sql_type[#All], '<SQL> '!$E$3, FALSE ) -> INTEGER | J109: Y | K109: Y | M109: {="ITM_"&UPPER(RIGHT(OFFSET(D109,S109,0),LEN(OFFSET(D109,S109,0))-4))&"_"&_xlfn.IFNA(_xlfn.IFS(K109="Y","PKEY",L109="Y","F"&UPPER(B109)),UPPER(B109))} -> ITM_SCP_PRODUCT_GENRE_PKEY | N109: =M109&","&B109&","&OFFSET(G109,0,VLOOKUP($C$5,SQL[#All],2,FALSE) ) &", -- "&D109 -> ITM_SCP_PRODUCT_GENRE_PKEY,key_scp_product_genre,INTEGER, -- 製品ジャンルID | O109: =LEFT(LEFT("KEY_"&M109&REPT(" ",$O$6),$O$6)&": Final[str] = """&M109&""""&REPT(" ",$O$5),$O$5)&"# "&D109 -> KEY_ITM_SCP_PRODUCT_GENRE_PKEY : Final[str] = "ITM_SCP_PRODUCT_GENRE_PKEY" # 製品ジャンルID | P109: =$B109 & " " & VLOOKUP($E109, sql_type[#All], '<SQL> '!$E$3, FALSE )& " " & IFERROR( IF($K109="", VLOOKUP(K109, sql_notnull[#All], '<SQL> '!$E$3, FALSE ), VLOOKUP($K109, sql_pk[], '<SQL> '!$E$3, FALSE ) ), "" ) & ", -- " &$D109 -> key_scp_product_genre INTEGER PRIMARY KEY, -- 製品ジャンルID | S109: -4
B110: =OFFSET( tbl_scp_product_genre[[#Headers],[key_scp_product_genre]], 0, ROWS( $A$109:A110 )-1 ) -> title_jp | C110: 日本語名称 | D110: 日本語名称 | E110: VARCHAR | F110: 20 | G110: =VLOOKUP($E110, sql_type[#All], '<SQL> '!$E$3, FALSE ) -> TEXT | J110: Y | M110: {="ITM_"&UPPER(RIGHT(OFFSET(D110,S110,0),LEN(OFFSET(D110,S110,0))-4))&"_"&_xlfn.IFNA(_xlfn.IFS(K110="Y","PKEY",L110="Y","F"&UPPER(B110)),UPPER(B110))} -> ITM_SCP_PRODUCT_GENRE_TITLE_JP | N110: =M110&","&B110&","&OFFSET(G110,0,VLOOKUP($C$5,SQL[#All],2,FALSE) ) &", -- "&D110 -> ITM_SCP_PRODUCT_GENRE_TITLE_JP,title_jp,TEXT, -- 日本語名称 | O110: =LEFT(LEFT("KEY_"&M110&REPT(" ",$O$6),$O$6)&": Final[str] = """&M110&""""&REPT(" ",$O$5),$O$5)&"# "&D110 -> KEY_ITM_SCP_PRODUCT_GENRE_TITLE_JP : Final[str] = "ITM_SCP_PRODUCT_GENRE_TITLE_JP" # 日本語名称 | S110: -5
B111: =OFFSET( tbl_scp_product_genre[[#Headers],[key_scp_product_genre]], 0, ROWS( $A$109:A111 )-1 ) -> title_en | C111: 英語名称 | D111: 英語名称 | E111: VARCHAR | F111: 20 | G111: =VLOOKUP($E111, sql_type[#All], '<SQL> '!$E$3, FALSE ) -> TEXT | J111: N | M111: {="ITM_"&UPPER(RIGHT(OFFSET(D111,S111,0),LEN(OFFSET(D111,S111,0))-4))&"_"&_xlfn.IFNA(_xlfn.IFS(K111="Y","PKEY",L111="Y","F"&UPPER(B111)),UPPER(B111))} -> ITM_SCP_PRODUCT_GENRE_TITLE_EN | N111: =M111&","&B111&","&OFFSET(G111,0,VLOOKUP($C$5,SQL[#All],2,FALSE) ) &", -- "&D111 -> ITM_SCP_PRODUCT_GENRE_TITLE_EN,title_en,TEXT, -- 英語名称 | O111: =LEFT(LEFT("KEY_"&M111&REPT(" ",$O$6),$O$6)&": Final[str] = """&M111&""""&REPT(" ",$O$5),$O$5)&"# "&D111 -> KEY_ITM_SCP_PRODUCT_GENRE_TITLE_EN : Final[str] = "ITM_SCP_PRODUCT_GENRE_TITLE_EN" # 英語名称 | S111: -6
B112: =OFFSET( tbl_scp_product_genre[[#Headers],[key_scp_product_genre]], 0, ROWS( $A$109:A112 )-1 ) -> hs_code | C112: HSコード | D112: HSコード | E112: TEXT | G112: =VLOOKUP($E112, sql_type[#All], '<SQL> '!$E$3, FALSE ) -> TEXT | J112: N | M112: {="ITM_"&UPPER(RIGHT(OFFSET(D112,S112,0),LEN(OFFSET(D112,S112,0))-4))&"_"&_xlfn.IFNA(_xlfn.IFS(K112="Y","PKEY",L112="Y","F"&UPPER(B112)),UPPER(B112))} -> ITM_SCP_PRODUCT_GENRE_HS_CODE | N112: =M112&","&B112&","&OFFSET(G112,0,VLOOKUP($C$5,SQL[#All],2,FALSE) ) &", -- "&D112 -> ITM_SCP_PRODUCT_GENRE_HS_CODE,hs_code,TEXT, -- HSコード | O112: =LEFT(LEFT("KEY_"&M112&REPT(" ",$O$6),$O$6)&": Final[str] = """&M112&""""&REPT(" ",$O$5),$O$5)&"# "&D112 -> KEY_ITM_SCP_PRODUCT_GENRE_HS_CODE : Final[str] = "ITM_SCP_PRODUCT_GENRE_HS_CODE" # HSコード | S112: -7
...

Sheet tbl_rules
A1: key_rule | B1: id_rule | C1: name_rule | D1: key_cat_sub | E1: link | F1: key_cat_state | G1: created_date | H1: update_date
A2: 1 | B2: PA011 | C2: 経営理念 | D2: 1 | E2: https://www4.kitei-kanri.jp/gf7/seikoepson/browse.php?action_treeList&rule=674&public_id=1 | F2: 1 | G2: 32874 | H2: 32874
A3: 2 | B3: PB011 | C3: 企業行動原則 | D3: 2 | E3: https://www4.kitei-kanri.jp/gf7/seikoepson/browse.php?action_treeList&rule=675&public_id=1 | F3: 1 | G3: 32874 | H3: 32874
A4: 3 | B4: PB111 | C4: エプソングループ製品安全に関する基本方針 | D4: 3 | E4: https://www4.kitei-kanri.jp/gf7/seikoepson/browse.php?action_treeList&rule=676&public_id=1 | F4: 1 | G4: 32874 | H4: 32874
A5: 4 | B5: PB121 | C5: エプソングループ労働安全衛生基本方針 | D5: 3 | E5: https://www4.kitei-kanri.jp/gf7/seikoepson/browse.php?action_treeList&rule=677&public_id=1 | F5: 1 | G5: 32874 | H5: 32874
A6: 5 | B6: PB131 | C6: エプソングループ人権方針 | D6: 3 | E6: https://www4.kitei-kanri.jp/gf7/seikoepson/browse.php?action_treeList&rule=678&public_id=1 | F6: 1 | G6: 32874 | H6: 32874
A7: 6 | B7: PB141 | C7: エプソングループAI倫理原則 | D7: 3 | E7: https://www4.kitei-kanri.jp/gf7/seikoepson/browse.php?action_treeList&rule=680&public_id=1 | F7: 1 | G7: 32874 | H7: 32874
A8: 7 | B8: PB151 | C8: 情報セキュリティー基本方針 | D8: 3 | E8: https://www4.kitei-kanri.jp/gf7/seikoepson/browse.php?action_treeList&rule=681&public_id=1 | F8: 1 | G8: 32874 | H8: 32874
A9: 8 | B9: PB161 | C9: エプソングループ調達基本方針 | D9: 3 | E9: https://www4.kitei-kanri.jp/gf7/seikoepson/browse.php?action_treeList&rule=682&public_id=1 | F9: 1 | G9: 32874 | H9: 32874
A10: 9 | B10: PC011 | C10: エプソングローバル社員行動規範 | D10: 4 | E10: https://www4.kitei-kanri.jp/gf7/seikoepson/browse.php?action_treeList&rule=683&public_id=1 | F10: 1 | G10: 32874 | H10: 32874
A11: 10 | B11: SA011 | C11: 定款 | D11: 5 | E11: https://www4.kitei-kanri.jp/gf7/seikoepson/browse.php?action_treeList&rule=684&public_id=1 | F11: 1 | G11: 32874 | H11: 32874
A12: 11 | B12: SA021 | C12: 株式取扱規則 | D12: 5 | E12: https://www4.kitei-kanri.jp/gf7/seikoepson/browse.php?action_treeList&rule=685&public_id=1 | F12: 1 | G12: 32874 | H12: 32874
A13: 12 | B13: SA031 | C13: コーポレートガバナンス基本方針 | D13: 5 | E13: https://www4.kitei-kanri.jp/gf7/seikoepson/browse.php?action_treeList&rule=686&public_id=1 | F13: 1 | G13: 32874 | H13: 32874
... A810: 809 | B810: GC-0025 | C810: TV特性(LCD5200) | D810: 59 | E810: https://ei-core-02.apo.epson.net/prozou/html/document/view/313537340000000000000000000000000000/1 | F810: 1 | G810: 32874 | H810: 43124
A811: 810 | B811: GC-0029 | C811: LCCOMズレ | D811: 59 | E811: https://ei-core-02.apo.epson.net/prozou/html/document/view/313537330000000000000000000000000000/1 | F811: 1 | G811: 32874 | H811: 43091 | S811: プロジェクターに限定
A812: 811 | B812: GC-0030 | C812: 上下ゴースト | D812: 59 | E812: https://ei-core-02.apo.epson.net/prozou/html/document/view/313537430000000000000000000000000000/1 | F812: 1 | G812: 32874 | H812: 43192 | S812: プロジェクターに限定
A813: 812 | B813: GC-0031 | C813: 透過率コントラスト | D813: 59 | E813: https://ei-core-02.apo.epson.net/prozou/html/document/view/313539480000000000000000000000000000/1 | F813: 1 | G813: 32874 | H813: 44944 | S813: プロジェクターに限定
A814: 813 | B814: GC-0032 | C814: 白線上黒線 | D814: 59 | E814: https://ei-core-02.apo.epson.net/prozou/html/document/view/313537370000000000000000000000000000/1 | F814: 1 | G814: 32874 | H814: 43124 | S814: プロジェクターに限定
A815: 814 | B815: GC-0033 | C815: ドメイン数値化 | D815: 59 | E815: https://ei-core-02.apo.epson.net/prozou/html/document/view/313537240000000000000000000000000000/1 | F815: 1 | G815: 32874 | H815: 43077 | S815: プロジェクターに限定
A816: 815 | B816: GC-0034 | C816: 入力端子容量 | D816: 59 | E816: https://ei-core-02.apo.epson.net/prozou/html/document/view/313537190000000000000000000000000000/1 | F816: 1 | G816: 32874 | H816: 43077 | S816: プロジェクターに限定
A817: 816 | B817: GC-0035 | C817: 液晶応答速度(LCD5200) | D817: 59 | E817: https://ei-core-02.apo.epson.net/prozou/html/document/view/313537230000000000000000000000000000/1 | F817: 1 | G817: 32874 | H817: 43077 | S817: プロジェクターに限定
A818: 817 | B818: GC-0036 | C818: 静止画ドメイン | D818: 59 | E818: https://ei-core-02.apo.epson.net/prozou/html/document/view/313537360000000000000000000000000000/1 | F818: 1 | G818: 32874 | H818: 43094 | S818: プロジェクターに限定
A819: 818 | B819: GC-0039 | C819: 動画ドメイン（手動測定） | D819: 59 | E819: https://ei-core-02.apo.epson.net/prozou/html/document/view/313537350000000000000000000000000000/1595552 | F819: 1 | G819: 32874 | H819: 45803.667 | S819: プロジェクターに限定
A820: 819 | B820: GC-0040 | C820: CV特性 | D820: 59 | E820: https://ei-core-02.apo.epson.net/prozou/html/document/view/313537170000000000000000000000000000/1 | F820: 1 | G820: 32874 | H820: 43069 | S820: プロジェクターに限定
A821: 820 | B821: GC-0041 | C821: 消費電流･消費電力 | D821: 59 | E821: https://ei-core-02.apo.epson.net/prozou/html/document/view/313537200000000000000000000000000000/1 | F821: 1 | G821: 32874 | H821: 43077 | S821: プロジェクターに限定
A822: 821 | B822: GC-0042 | C822: 絶対最大定格 | D822: 59 | E822: https://ei-core-02.apo.epson.net/prozou/html/document/view/313537210000000000000000000000000000/1 | F822: 1 | G822: 32874 | H822: 43077 | S822: プロジェクターに限定
... A826: 825 | B826: GC-0052 | C826: 動画縦帯 | D826: 59 | E826: https://ei-core-02.apo.epson.net/prozou/html/document/view/313537220000000000000000000000000000/1 | F826: 1 | G826: 32874 | H826: 43077 | S826: プロジェクターに限定
A827: 826 | B827: GC-0058 | C827: アプリケーションCD同梱業務処理基準 | D827: 59 | E827: https://ei-core-02.apo.epson.net/prozou/html/document/view/313537100000000000000000000000000000/1 | F827: 1 | G827: 32874 | H827: 42796
A828: 827 | B828: GC-0060 | C828: 光リーク画素ムラ | D828: 59 | E828: https://ei-core-02.apo.epson.net/prozou/html/document/view/313537530000000000000000000000000000/1 | F828: 1 | G828: 32874 | H828: 43272 | S828: プロジェクターに限定
A829: 828 | B829: GC-0061 | C829: 表示ムラ | D829: 59 | E829: https://ei-core-02.apo.epson.net/prozou/html/document/view/313537870000000000000000000000000000/1 | F829: 1 | G829: 32874 | H829: 43521 | S829: プロジェクターに限定
A830: 829 | B830: GC-0062 | C830: 周辺光再反射 | D830: 59 | E830: https://ei-core-02.apo.epson.net/prozou/html/document/view/313537550000000000000000000000000000/1 | F830: 1 | G830: 32874 | H830: 43272 | S830: プロジェクターに限定
A831: 830 | B831: GC-0063 | C831: 井桁ムラ | D831: 59 | E831: https://ei-core-02.apo.epson.net/prozou/html/document/view/313537570000000000000000000000000000/1 | F831: 1 | G831: 32874 | H831: 43272 | S831: プロジェクターに限定
A832: 831 | B832: GC-0064 | C832: フックけられ | D832: 59 | E832: https://ei-core-02.apo.epson.net/prozou/html/document/view/313537580000000000000000000000000000/1 | F832: 1 | G832: 32874 | H832: 43272 | S832: プロジェクターに限定
A833: 832 | B833: GC-0065 | C833: 左右画素ムラ | D833: 59 | E833: https://ei-core-02.apo.epson.net/prozou/html/document/view/313537540000000000000000000000000000/1 | F833: 1 | G833: 32874 | H833: 43272 | S833: プロジェクターに限定
A834: 833 | B834: GC-0066 | C834: 配向性画素ムラ | D834: 59 | E834: https://ei-core-02.apo.epson.net/prozou/html/document/view/313537560000000000000000000000000000/1 | F834: 1 | G834: 32874 | H834: 43272 | S834: プロジェクターに限定
A835: 834 | B835: GC-0067 | C835: パネル表面温度 | D835: 59 | E835: https://ei-core-02.apo.epson.net/prozou/html/document/view/313537710000000000000000000000000000/1 | F835: 1 | G835: 32874 | H835: 43340 | S835: プロジェクターに限定
A836: 835 | B836: GC-0071 | C836: ゴースト・VDDXマージン | D836: 59 | E836: https://ei-core-02.apo.epson.net/prozou/html/document/view/313537250000000000000000000000000000/1 | F836: 1 | G836: 32874 | H836: 43182 | S836: プロジェクターに限定
A837: 836 | B837: GC-0072 | C837: 帯ムラマージン | D837: 59 | E837: https://ei-core-02.apo.epson.net/prozou/html/document/view/313537260000000000000000000000000000/1 | F837: 1 | G837: 32874 | H837: 43182 | S837: プロジェクターに限定
A838: 837 | B838: GC-0073 | C838: 高温画素ズレ | D838: 59 | E838: https://ei-core-02.apo.epson.net/prozou/html/document/view/313537280000000000000000000000000000/1 | F838: 1 | G838: 32874 | H838: 43077 | S838: プロジェクターに限定
A839: 838 | B839: GC-0074 | C839: FPC斜め引っ張り | D839: 59 | E839: https://ei-core-02.apo.epson.net/prozou/html/document/view/313537290000000000000000000000000000/1 | F839: 1 | G839: 32874 | H839: 43077 | S839: プロジェクターに限定
... A843: 842 | B843: GC-0078 | C843: 投影焼付き(自動測定） | D843: 59 | E843: https://ei-core-02.apo.epson.net/prozou/html/document/view/313537380000000000000000000000000000/1 | F843: 1 | G843: 32874 | H843: 43096 | S843: プロジェクターに限定
A844: 843 | B844: GC-0079 | C844: GC-0079（デザイン）顧客個人情報管理基準 | D844: 59 | E844: https://ei-core-02.apo.epson.net/prozou/html/document/view/313539630000000000000000000000000000/1 | F844: 1 | G844: 32874 | H844: 44999
A845: 844 | B845: GC-0080 | C845: 上下輝度ムラ | D845: 59 | E845: https://ei-core-02.apo.epson.net/prozou/html/document/view/313537410000000000000000000000000000/1 | F845: 1 | G845: 32874 | H845: 43189 | S845: プロジェクターに限定
A846: 845 | B846: GC-0081 | C846: (デザイン）現品管理品管理基準 | D846: 59 | E846: https://ei-core-02.apo.epson.net/prozou/html/document/view/313537440000000000000000000000000000/1 | F846: 1 | G846: 32874 | H846: 43210
A847: 846 | B847: GC-0082 | C847: (デザイン）職場管理品管理基準 | D847: 59 | E847: https://ei-core-02.apo.epson.net/prozou/html/document/view/313537740000000000000000000000000000/1 | F847: 1 | G847: 32874 | H847: 43388
A848: 847 | B848: GC-0083 | C848: GC-0083（デザイン）外部委託業務の個人情報運用基準 | D848: 59 | E848: https://ei-core-02.apo.epson.net/prozou/html/document/view/313539640000000000000000000000000000/1 | F848: 1 | G848: 32874 | H848: 44999
A849: 848 | B849: GC-0084 | C849: （デザイン）情報資産管理基準 | D849: 59 | E849: https://ei-core-02.apo.epson.net/prozou/html/document/view/313537450000000000000000000000000000/1 | F849: 1 | G849: 32874 | H849: 43191
A850: 849 | B850: GC-0085 | C850: GC-0085(デザイン)外観３Dデータ管理基準 | D850: 59 | E850: https://ei-core-02.apo.epson.net/prozou/html/document/view/313537990000000000000000000000000000/1 | F850: 1 | G850: 32874 | H850: 43706
A851: 850 | B851: GC-0087 | C851: GC-0087(デザイン)意匠出願処理基準 | D851: 59 | E851: https://ei-core-02.apo.epson.net/prozou/html/document/view/313537500000000000000000000000000000/1 | F851: 1 | G851: 32874 | H851: 43238
A852: 851 | B852: GC-0088 | C852: （デザイン）CUD認証対応基準 | D852: 59 | E852: https://ei-core-02.apo.epson.net/prozou/html/document/view/313539570000000000000000000000000000/1 | F852: 1 | G852: 32874 | H852: 44978
A853: 852 | B853: GC-0089 | C853: （デザイン）版下作成業務推進基準（ID編） | D853: 59 | E853: https://ei-core-02.apo.epson.net/prozou/html/document/view/313537600000000000000000000000000000/1452976 | F853: 1 | G853: 32874 | H853: 45730.543
A854: 853 | B854: GC-0090 | C854: （デザイン）輸出入手続き基準 | D854: 59 | E854: https://ei-core-02.apo.epson.net/prozou/html/document/view/313537640000000000000000000000000000/1452788 | F854: 1 | G854: 32874 | H854: 45730.543
A855: 854 | B855: GC-0092 | C855: （デザイン）モック管理品管理基準 | D855: 59 | E855: https://ei-core-02.apo.epson.net/prozou/html/document/view/313537760000000000000000000000000000/1453097 | F855: 1 | G855: 32874 | H855: 45730.543
A856: 855 | B856: GC-0093 | C856: 完成体評価 | D856: 59 | E856: https://ei-core-02.apo.epson.net/prozou/html/document/view/313537790000000000000000000000000000/1 | F856: 1 | G856: 32874 | H856: 43553 | S856: プロジェクターにのみ限定
A857: 856 | B857: GC-0094 | C857: 技術情報サイトへの回答基準 | D857: 61 | E857: https://ei-core-02.apo.epson.net/prozou/html/document/view/313537860000000000000000000000000000/1 | F857: 1 | G857: 32874 | H857: 43517
A858: 857 | B858: GC-0095 | C858: 製品外観図制定_業務処理標準 | D858: 59 | E858: https://ei-core-02.apo.epson.net/prozou/html/document/view/313539830000000000000000000000000000/1862842 | F858: 1 | G858: 32874 | H858: 45918.647
A859: 858 | B859: GC-0096 | C859: [ライトバルブ]_耐光性寿命推定プロセス | D859: 59 | E859: https://ei-core-02.apo.epson.net/prozou/html/document/view/313539530000000000000000000000000000/1 | F859: 1 | G859: 32874 | H859: 44957
A860: 859 | B860: GC-0097 | C860: デザインレビュー資料保管業務処理基準_ | D860: 62 | E860: https://ei-core-02.apo.epson.net/prozou/html/document/view/313540610000000000000000000000000000/1 | F860: 1 | G860: 32874 | H860: 45461
A861: 860 | B861: GC-0098 | C861: (メカ設計）要素TDR運用基準(TDR1~TDR2) | D861: 59 | E861: https://ei-core-02.apo.epson.net/prozou/html/document/view/313539840000000000000000000000000000/1784190 | F861: 1 | G861: 32874 | H861: 45890.73
A862: 861 | B862: GC-0099 | C862: Agentログ取り扱い業務処理基準 | D862: 59 | E862: https://ei-core-02.apo.epson.net/prozou/html/document/view/313538300000000000000000000000000000/1 | F862: 1 | G862: 32874 | H862: 44014
A863: 862 | B863: GC-0100 | C863: 新製品立ち上げ手順（基板） | D863: 59 | E863: https://ei-core-02.apo.epson.net/prozou/html/document/view/313540130000000000000000000000000000/1 | F863: 1 | G863: 32874 | H863: 45307
A864: 863 | B864: GC-0102 | C864: （デザイン）製品本体ロゴ表記基準 | D864: 59 | E864: https://ei-core-02.apo.epson.net/prozou/html/document/view/313538210000000000000000000000000000/1 | F864: 1 | G864: 32874 | H864: 43852
A865: 864 | B865: GC-0103 | C865: アライアンス系認証業務処理基準 | D865: 59 | E865: https://ei-core-02.apo.epson.net/prozou/html/document/view/313538890000000000000000000000000000/1 | F865: 1 | G865: 32874 | H865: 44476 | S865: ISO文書では無いのに、なぜISO内部監査にて指摘されているのか？
A866: 865 | B866: GC-0104 | C866: （デザイン）外装デザインガイドライン | D866: 59 | E866: https://ei-core-02.apo.epson.net/prozou/html/document/view/313539130000000000000000000000000000/1 | F866: 1 | G866: 32874 | H866: 44747
A867: 866 | B867: GC-0106 | C867: [ﾗｲﾄﾊﾞﾙﾌﾞ]耐光性評価試験_業務処理基準 | D867: 59 | E867: https://ei-core-02.apo.epson.net/prozou/html/document/view/313539060000000000000000000000000000/1 | F867: 1 | G867: 32874 | H867: 44652
A868: 867 | B868: GC-0107 | C868: ソフトウェア機能実装判定会議運用基準 | D868: 59 | E868: https://ei-core-02.apo.epson.net/prozou/html/document/view/313538620000000000000000000000000000/1 | F868: 1 | G868: 32874 | H868: 44166
A869: 868 | B869: GC-0108 | C869: （メカ設計）先行開発プロセス基準 | D869: 59 | E869: https://ei-core-02.apo.epson.net/prozou/html/document/view/313538640000000000000000000000000000/1 | F869: 1 | G869: 32874 | H869: 44186
A870: 869 | B870: GC-0109 | C870: レーザー光源プロジェクターのレーザー安全評価に関する業務処理基準 | D870: 59 | E870: https://ei-core-02.apo.epson.net/prozou/html/document/view/313538710000000000000000000000000000/1 | F870: 1 | G870: 32874 | H870: 44292
A871: 870 | B871: GC-0111 | C871: (メカ設計）要素TDR運用基準(TDR3A/3~TDR4) | D871: 59 | E871: https://ei-core-02.apo.epson.net/prozou/html/document/view/313538730000000000000000000000000000/1 | F871: 1 | G871: 32874 | H871: 44341
A872: 871 | B872: GC-0112 | C872: 価値積み上げ型ソフトウェア開発基準 | D872: 59 | E872: https://ei-core-02.apo.epson.net/prozou/html/document/view/313538810000000000000000000000000000/1 | F872: 1 | G872: 32874 | H872: 44468
A873: 872 | B873: GC-0113 | C873: （メカ設計）過去トラ情報登録フロー_業務処理基準 | D873: 59 | E873: https://ei-core-02.apo.epson.net/prozou/html/document/view/313539850000000000000000000000000000/1 | F873: 1 | G873: 32874 | H873: 45091
A874: 873 | B874: GC-0114 | C874: （商品化推進）企画尖鋭化会議_業務処理基準 | D874: 59 | E874: https://ei-core-02.apo.epson.net/prozou/html/document/view/313538960000000000000000000000000000/1 | F874: 1 | G874: 32874 | H874: 44540
A875: 874 | B875: GC-0115 | C875: 安全/EMC/電波法認可取得国決定基準 | D875: 59 | E875: https://ei-core-02.apo.epson.net/prozou/html/document/view/313540090000000000000000000000000000/1371107 | F875: 1 | G875: 32874 | H875: 45679.653
A876: 875 | B876: GC-0116 | C876: 新製品立ち上げ業務手順（MDリーダー） | D876: 59 | E876: https://ei-core-02.apo.epson.net/prozou/html/document/view/313540620000000000000000000000000000/1493021 | F876: 1 | G876: 32874 | H876: 45754.636
A877: 876 | B877: GC-0117 | C877: 実装設計業務処理基準 | D877: 59 | E877: https://ei-core-02.apo.epson.net/prozou/html/document/view/313539400000000000000000000000000000/1 | F877: 1 | G877: 32874 | H877: 44903
... A1416: 1415 | B1416: KH-Z99-0006 | C1416: ErP_Lot6/26_法令対応基準 | D1416: 104 | E1416: https://ei-core-02.apo.epson.net/prozou/html/document/view/313535700000000000000000000000000000/1 | F1416: 1 | G1416: 32874 | H1416: 44522

Sheet tbl_cat_type
A1: key_cat_type | B1: title_jp | C1: title_en | D1: path
A2: 1 | B2: エプソン例規集 | C2: RULES_CORP | D2: corp_rules
A3: 2 | B3: 全社EQS | C3: EQS_CORP | D3: corp_eqs
A4: 3 | B4: VP事業部基準 | C4: RULES_VP | D4: vp_rules
A5: 4 | B5: VP事業部EQS | C5: EQS_VP | D5: vp_eqs
A6: 5 | B6: VP業務処理基準 | C6: OPS_VP | D6: vp_ops
A7: 6 | B7: VP規格・標準 | C7: STANDARD_VP | D7: vp_standard

Sheet tbl_cat_major
A1: key_cat_major | B1: title_jp | C1: title_en | D1: key_cat_type | E1: path
A2: 1 | B2: 理念 | C2: PHILOSOPHY | D2: 1 | E2: philosophy | F2: =TEXT(tbl_cat_major[[#This Row],[key_cat_major]],"")
A3: 2 | B3: SEC規程 | C3: OFFICE | D3: 1 | E3: office | F3: =TEXT(tbl_cat_major[[#This Row],[key_cat_major]],"")
A4: 3 | B4: グループ規程 | C4: GROUP | D4: 1 | E4: group | F4: =TEXT(tbl_cat_major[[#This Row],[key_cat_major]],"")
A5: 4 | B5: 安全性 | C5: SAFETY | D5: 2 | E5: safety | F5: =TEXT(tbl_cat_major[[#This Row],[key_cat_major]],"")
A6: 5 | B6: 含有化学物質 | C6: CHEMICAL | D6: 2 | E6: chem | F6: =TEXT(tbl_cat_major[[#This Row],[key_cat_major]],"")
A7: 6 | B7: 化学製品 | C7: CHEMICAL_PRODUCTS | D7: 2 | E7: chem_prod | F7: =TEXT(tbl_cat_major[[#This Row],[key_cat_major]],"")
A8: 7 | B8: 環境 | C8: ENVIROMENT | D8: 2 | E8: env | F8: =TEXT(tbl_cat_major[[#This Row],[key_cat_major]],"")
A9: 8 | B9: EMC | C9: EMC | D9: 2 | E9: emc | F9: =TEXT(tbl_cat_major[[#This Row],[key_cat_major]],"")
A10: 9 | B10: セキュリティ | C10: SECURITY | D10: 2 | E10: security | F10: =TEXT(tbl_cat_major[[#This Row],[key_cat_major]],"")
A11: 10 | B11: 輸送 | C11: TRANSPORT | D11: 2 | E11: trans | F11: =TEXT(tbl_cat_major[[#This Row],[key_cat_major]],"")
A12: 11 | B12: ウィスカ | C12: Wisker | D12: 2 | E12: wisker | F12: =TEXT(tbl_cat_major[[#This Row],[key_cat_major]],"")
A13: 12 | B13: AI | C13: AI | D13: 2 | E13: ai | F13: =TEXT(tbl_cat_major[[#This Row],[key_cat_major]],"")
... A40: 39 | B40: 一般 | C40: GENERAL | D40: 6 | E40: general | F40: =TEXT(tbl_cat_major[[#This Row],[key_cat_major]],"")

Sheet tbl_cat_sub
A1: key_cat_sub | B1: title_jp | C1: title_en | D1: key_cat_major | E1: path
A2: 1 | B2: 経営理念 | C2: MANAGEMENT_PHILOSOPHY | D2: 1 | E2: mgmt_phil
A3: 2 | B3: 企業行動原則 | C3: CORPORATE_ACTION_PRINCIPLES | D3: 1 | E3: corp_actp
A4: 3 | B4: 方針類 | C4: POLICY_CATEGORY | D4: 1 | E4: pol_cat
A5: 4 | B5: 社員行動規範 | C5: EMPLOYEE_CODE_OF_CONDUCT | D5: 1 | E5: emp_coc
A6: 5 | B6: 定款と付属規程 | C6: ARTICLES_OF_INCORPORATION_AND_SUPPLEMENTARY_REGULATIONS | D6: 2 | E6: aoi_supp
A7: 6 | B7: ガバナンス | C7: GOVERNANCE | D7: 2 | E7: gov
A8: 7 | B8: コンプライアンス | C8: COMPLIANCE | D8: 2 | E8: comp
A9: 8 | B9: 規程管理 | C9: PROCEDURE_MANAGEMENT | D9: 2 | E9: proc_mgmt
A10: 9 | B10: 組織分掌 | C10: DIVISION_OF_ORGANIZATION | D10: 2 | E10: div_org
A11: 10 | B11: 経営会議 | C11: MANAGEMENT_MEETING | D11: 2 | E11: mgmt_mt
A12: 11 | B12: 職務権限 | C12: AUTHORITY | D12: 2 | E12: auth
A13: 12 | B13: 役員関連 | C13: OFFICER_RELATED | D13: 2 | E13: off_rel
... A105: 104 | B105: - | C105: - | D105: 39 | E105: null

Sheet tbl_cat_state
A1: key_cat_state | B1: title_jp | C1: title_en
A2: 0 | B2: 作成中 | C2: Draft
A3: 1 | B3: 制定版 | C3: Active
A4: 2 | B4: 廃止 | C4: Retired

Sheet tbl_request
A1: key_req | B1: key_rule | C1: id_cap | D1: title_capter | E1: title_section | F1: top_body | G1: low_body | H1: top_tbl | I1: top_fig | J1: low_tbl | K1: low_fig | L1: lead_time | M1: reference | N1: created_date | O1: update_date | P1: key_cat_request | Q1: key_cat_phase | R1: scope_product_genre | S1: scope_service_genre | T1: scope_equipment | U1: scope_pii | V1: scope_design_domain | W1: unique_search
A2: 1 | B2: 575 | C2: 1 | D2: プラグ残留電圧 | E2: 試験条件 | F2: ① 製品状態：プラグ残留電圧が最大となるよう設定する。 ② 周囲温度：常温常湿 ③ 対象製品：商用電源を使用する製品
A3: 2 | B3: 575 | C3: 1 | D3: プラグ残留電圧 | E3: 試験方法 | F3: ① 製品を１分以上動作させて電源プラグ抜き、１秒後のプラグに残留する電圧をストレージオシロスコープ等で測定する。 ② 測定は、放電するのに充分な時間間隔をおいて１０回以上おこない、その最大値を測定値とする。
A4: 3 | B4: 575 | C4: 1 | D4: プラグ残留電圧 | E4: 判定基準 | F4: プラグ残留電圧は時定数（ｔｉｍｅ ｃｏｎｓｔａｎｔ）１秒以下であること。 図のようにプラグに残留する電圧が３６．８％まで降下するのに1秒以下でなければならない。

Sheet tbl_cat_request
A1: key_cat_request | B1: title_jp | C1: title_en | D1: key_cat_req_type | E1: req_type
A2: 0 | B2: 全般 | D2: 0 | E2: 商品化に関わらない内容
A3: 1 | B3: 試験条件 | D3: 1 | E3: 商品化アクション
A4: 2 | B4: 試験内容 | D4: 2 | E4: 商品化説明
A5: 3 | B5: 合格基準 | D5: 3 | E5: 商品化チェック項目
A6: 4 | B6: 適合範囲 | D6: 4 | E6: 商品化アクション＆チェック項目

Sheet tbl_cat_phase
A1: key_cat_phase | B1: title_jp | C1: title_en
A2: 0 | B2: ~DR0
A3: 1 | B3: ~DR1
A4: 2 | B4: ~DR2
A5: 3 | B5: ~DR3
A6: 4 | B6: ~DR4
A7: 5 | B7: ~DR5

Sheet tbl_scp_sales_region
A1: key_scp_sales_region | B1: title_jp | C1: title_en | D1: country_code_2 | E1: country_code_3
A2: 0 | B2: アメリカ | C2: United States | D2: US | E2: USA
A3: 1 | B3: カナダ | C3: Canada | D3: CA | E3: CAN
A4: 2 | B4: EU | C4: EU | D4: EU | E4: —
A5: 3 | B5: フランス | C5: France | D5: FR | E5: FRA
A6: 4 | B6: イタリア | C6: Italy | D6: IT | E6: ITA
A7: 5 | B7: スペイン | C7: Spain | D7: ES | E7: ESP
A8: 6 | B8: 日本 | C8: Japan | D8: JP | E8: JPN
A9: 7 | B9: トルコ | C9: Turkey | D9: TR | E9: TUR
A10: 8 | B10: ウクライナ | C10: Ukraine | D10: UA | E10: UKR
A11: 9 | B11: 中国 | C11: China | D11: CN | E11: CHN
A12: 10 | B12: インド | C12: India | D12: IN | E12: IND
A13: 11 | B13: 台湾 | C13: Taiwan | D13: TW | E13: TWN
... A29: 27 | B29: アルゼンチン | C29: Argentina | D29: AR | E29: ARG

Sheet tbl_scp_product_genre
A1: key_scp_product_genre | B1: title_jp | C1: title_en | D1: hs_code
A2: 0 | B2: 全部
A3: 1 | B3: LCP本体
A4: 2 | B4: LCPオプション
A5: 3 | B5: スクリーン
A6: 4 | B6: 書画カメラ

Sheet tbl_scp_service_genre
A1: key_scp_service_genre | B1: title_jp | C1: title_en
A2: 0 | B2: PCアプリ
A3: 1 | B3: FW
A4: 2 | B4: SDK
A5: 3 | B5: Webページ
A6: 4 | B6: Webサービス

Sheet tbl_scp_equipment
A1: key_scp_equipment | B1: title_jp | C1: title_en
A2: 0 | B2: ACDC変換
A3: 1 | B3: ACアダプター
A4: 2 | B4: リチウムイオン電池
A5: 3 | B5: その他電池

Sheet tbl_scp_pii
A1: key_scp_pii | B1: title_jp | C1: title_en
A2: 0 | B2: 無し
A3: 1 | B3: 個人情報
A4: 2 | B4: 個人情報レベル2

Sheet tbl_scp_design_domain
A1: key_scp_design_domain | B1: title_jp | C1: title_en
A2: 0 | B2: メカ | C2: Mecha
A3: 1 | B3: エレキ | C3: Elec
A4: 2 | B4: ソフト | C4: Soft
A5: 3 | B5: 表示 | C5: Display
A6: 4 | B6: 梱包 | C6: Package
A7: 5 | B7: 認証 | C7: Certification
A8: 6 | B8: 製造 | C8: Manufacturing
